[
    {
        "Full Post": "liebe gemeinde, in einem von mir einst häufig besuchten forum rund um das thema musik war einer der erfolgreichsten threads, der nichts weiter tat, als abzufragen, was die leute gerade hören. nicht gestern, nicht morgen. zu diesem zeitpunkt. das könnte doch auch hier ganz hilfreich sein und neben den anderen seiten im netz, die sich mit einer sortenübersicht beschäftigen, eine übersicht bringen, die von vielen leuten zusammengetragen wird. so ergeben sich zwangsläufig perpektiven, die ein autor allein nicht haben wird. so ähnlich wie die erfahrungsberichte. ich schlage als vor nach folgendem muster vorzugehen: Name der Bohne: Mocambo Oro Packungsgröße: 1000 Gramm Gemahlen und Bezogen mit: Anfim Best/Vibiemme Domobar Gekauft am: Mitte April MHD: 11/09 Eigenschaften: (hier tue ich mich gerade etwas schwer, da ich ihn sehr unterschiedlich finde und nichtmal sicher, ob ich nochmal kaufen würde. aber ich versuch's mal) Bohnen dunkel geröstet, Einstellung des Mahlgrads nach 200 Gramm Rumprobieren recht stabil. Sehr dunkle Schokoladearomen mit nur wenig Frucht, wenig säure. Crema stabil aber trotz sämigen Auslaufs recht flüssiger Espresso. Im Cappuccino kräftig und die fehlende Fruchtigkeit könnte ich jetzt fast vermissen. (genug prosa) Wieder kaufen: Eher nein. so, das wäre so ein muster. aber ich würde vorschlagen, AUSSCHLIESSLICH bohnen zu beschreiben, die wirklich dieser tage in der mühle sind. dafür gerne auch im wochenrhythmus immer die gleiche, falls sich veränderungen von packung zu packung ergeben. nachtrag: vermutlich wäre es sinnvoll, noch das mischungsverhältnis aus arabica und robusta beizuschreiben, vielleicht direkt hinter den namen. so man es denn weiß, ich weiß es beim mocambo nicht und will es auch nicht irgendwo einfach abschreiben.",
        "Name": "Mocambo Oro",
        "Packungsgröße": "1000 Gramm",
        "Maschine": "Anfim Best/Vibiemme Domobar",
        "Gekauft am": "Mitte April",
        "MHD": "11/09",
        "Eigenschaften": "(hier tue ich mich gerade etwas schwer, da ich ihn sehr unterschiedlich finde und nichtmal sicher, ob ich nochmal kaufen würde. aber ich versuch's mal) Bohnen dunkel geröstet, Einstellung des Mahlgrads nach 200 Gramm Rumprobieren recht stabil. Sehr dunkle Schokoladearomen mit nur wenig Frucht, wenig säure. Crema stabil aber trotz sämigen Auslaufs recht flüssiger Espresso. Im Cappuccino kräftig und die fehlende Fruchtigkeit könnte ich jetzt fast vermissen. (genug prosa)",
        "Geschmack": "",
        "Wiederkaufen": "Eher nein. so, das wäre so ein muster. aber ich würde vorschlagen, AUSSCHLIESSLICH bohnen zu beschreiben, die wirklich dieser tage in der mühle sind. dafür gerne auch im wochenrhythmus immer die gleiche, falls sich veränderungen von packung zu packung ergeben. nachtrag: vermutlich wäre es sinnvoll, noch das mischungsverhältnis aus arabica und robusta beizuschreiben, vielleicht direkt hinter den namen. so man es denn weiß, ich weiß es beim mocambo nicht und will es auch nicht irgendwo einfach abschreiben."
    },
    {
        "Full Post": "AW: Ich trinke gerade diesen Espresso.... Name der Bohne: Fausto Giasing Packungsgröße: 500 Gramm Gemahlen und Bezogen mit: Lux/Oscar Gekauft am: Anfang Mai MHD: 05/09 Eigenschaften: Einstellung des Mahlgrads nach 20 g sehr stabil. Fruchtig \"aprikosig\", sehr mild, kräftiger bei etwas mehr Temperatur. Crema gut. Gleicher Eindruck im Cappuccino. Sehr unkomplizierter Kaffee. Wieder kaufen: Ja. Gruss Plempel",
        "Name": "Fausto Giasing",
        "Packungsgröße": "500 Gramm",
        "Maschine": "Lux/Oscar",
        "Gekauft am": "Anfang Mai",
        "MHD": "05/09",
        "Eigenschaften": "Einstellung des Mahlgrads nach 20 g sehr stabil. Fruchtig \"aprikosig\", sehr mild, kräftiger bei etwas mehr Temperatur. Crema gut. Gleicher Eindruck im Cappuccino. Sehr unkomplizierter Kaffee.",
        "Geschmack": "",
        "Wiederkaufen": "Ja. Gruss Plempel"
    },
    {
        "Full Post": "AW: Ich trinke gerade diesen Espresso.... Name der Bohne: Mocambo Oro Packungsgröße: 1000 Gramm Gemahlen und Bezogen mit: Anfim Best/Vibiemme Domobar Gekauft am: Mitte April MHD: 11/09 Eigenschaften: tja, muss vielleicht nochmal neu schreiben. gerade eben mit mehr druck getampert. ziemlich amtliche eckdaten: 25 sec für 60 ml (doppio) aus dem zweierauslauf. schokolade. dunkle, dunkle schokolade (mit zucker getrunken). lang anhaltend im mund, nennen wir es ruhig finish. sehr stabile crema, immer noch kaum säure, mildeste fruchtigkeit. ich merk schon: hartes business, espresso zu verkosten. Wieder kaufen: Eher nein. Nun mit dem Zusatz, dass er mir zu divenhaft ist, da ich schöne ergebnisse auch schon mit weniger Hingabe erzielt habe.",
        "Name": "Mocambo Oro",
        "Packungsgröße": "1000 Gramm",
        "Maschine": "Anfim Best/Vibiemme Domobar",
        "Gekauft am": "Mitte April",
        "MHD": "11/09",
        "Eigenschaften": "tja, muss vielleicht nochmal neu schreiben. gerade eben mit mehr druck getampert. ziemlich amtliche eckdaten: 25 sec für 60 ml (doppio) aus dem zweierauslauf. schokolade. dunkle, dunkle schokolade (mit zucker getrunken). lang anhaltend im mund, nennen wir es ruhig finish. sehr stabile crema, immer noch kaum säure, mildeste fruchtigkeit. ich merk schon: hartes business, espresso zu verkosten.",
        "Geschmack": "",
        "Wiederkaufen": "Eher nein. Nun mit dem Zusatz, dass er mir zu divenhaft ist, da ich schöne ergebnisse auch schon mit weniger Hingabe erzielt habe."
    },
    {
        "Full Post": "AW: Ich trinke gerade diesen Espresso.... Name der Bohne: Mozia von Walter Packungsgröße: 500 Gramm Gemahlen und Bezogen mit: Mazzer Mini E und ner Butterfly Gekauft am: am 3.5 gröstet MHD: Eigenschaften: Hatte ja schon so einige von Walter in der Mazzer, aber dieser ist die beste Mischung die ich bisher von Ihm. Möchte zur Zeit gar keinen Cappu mehr trinken, obwohl meine Frau sagt er wär s** lecker! Sehr Schokolastig mit einer sehr feinen aber dennoch stets präsenten Säure. Sehr rund. Mag eigentlich immer viel Zucker, nehme aber beim Mozia eher weniger! Sehr unkomplizierter Kaffee. Wieder kaufen: Auf jeden Fall! LG Dominik",
        "Name": "Mozia von Walter",
        "Packungsgröße": "500 Gramm",
        "Maschine": "Mazzer Mini E und ner Butterfly",
        "Gekauft am": "am 3.5 gröstet",
        "MHD": ": Hatte ja schon so einige von Walter in der Mazzer, aber dieser ist die beste Mischung die ich bisher von Ihm. Möchte zur Zeit gar keinen Cappu mehr trinken, obwohl meine Frau sagt er wär s** lecker! Sehr Schokolastig mit einer sehr feinen aber dennoch stets präsenten Säure. Sehr rund. Mag eigentlich immer viel Zucker, nehme aber beim Mozia eher weniger! Sehr unkomplizierter Kaffee.",
        "Eigenschaften": "Hatte ja schon so einige von Walter in der Mazzer, aber dieser ist die beste Mischung die ich bisher von Ihm. Möchte zur Zeit gar keinen Cappu mehr trinken, obwohl meine Frau sagt er wär s** lecker! Sehr Schokolastig mit einer sehr feinen aber dennoch stets präsenten Säure. Sehr rund. Mag eigentlich immer viel Zucker, nehme aber beim Mozia eher weniger! Sehr unkomplizierter Kaffee.",
        "Geschmack": "",
        "Wiederkaufen": "Auf jeden Fall! LG Dominik"
    },
    {
        "Full Post": "AW: Ich trinke gerade diesen Espresso.... Name der Bohne: Kaffee vom Schneid, Espresso Pinoro Packungsgröße: 500 Gramm Gemahlen und Bezogen mit: Lux/Oscar Gekauft am: Mitte Mai MHD: vor Ort frisch eingetütet Eigenschaften: Einstellung des Mahlgrads unkompliziert. Bei \"normaler\" Temperatur recht unspektakulär (nicht abwertend gemeint). Ohne, bzw. mit kurzem Leerbezug geht's dann schon zur Sache: Wild, eine Mischung aus Herdkanne und Autobahnraststätte. Crema gut. Verliert sich ein bisschen im Cappuccino. Sehr \"eigener\" Kaffee, love it or leave it. Wieder kaufen: Ja. Gruss Plempel",
        "Name": "Kaffee vom Schneid, Espresso Pinoro",
        "Packungsgröße": "500 Gramm",
        "Maschine": "Lux/Oscar",
        "Gekauft am": "Mitte Mai",
        "MHD": "vor Ort frisch eingetütet",
        "Eigenschaften": "Einstellung des Mahlgrads unkompliziert. Bei \"normaler\" Temperatur recht unspektakulär (nicht abwertend gemeint). Ohne, bzw. mit kurzem Leerbezug geht's dann schon zur Sache: Wild, eine Mischung aus Herdkanne und Autobahnraststätte. Crema gut. Verliert sich ein bisschen im Cappuccino. Sehr \"eigener\" Kaffee, love it or leave it.",
        "Geschmack": "",
        "Wiederkaufen": "Ja. Gruss Plempel"
    },
    {
        "Full Post": "AW: Ich trinke gerade diesen Espresso.... Name der Bohne: Pascucci Classic Packungsgröße: 1000 Gramm Gemahlen und Bezogen mit: Anfim Best/Domobar Gekauft am: Anfang Mai MHD: 30. September 09, geröstet laut deutschem Vertrieb Ende März 08 Eigenschaften: Einstellung des Mahlgrads stabil. Einmal gefunden, änderts sich scheinbar nicht so viel. Zum glück, bin ja faul. Habe ihn gekauft, weil er bei espressosorten.de zu den Lieblingen für Cappuccino zählt. Er kommt wirklich dick raus aus dem Auslauf. So dick, dass ich immer denke, er kommt zu schnell raus, aber die Parameter sind soweit okay. (Ich stoppe gelegentlich und schaue auf die Füllmenge. Exakt nachmessen ist nicht meine Welt). Ich finde ihn recht fruchtarm. Im Cappuccino setzt er sich prima durch wie versprochen. Er bleibt dort für meinen Geschmack recht - hm - ja, reduziert aufs Geröstete. Dunkel. Kein Schoko, Nuss oder ähnliches. Auf jeden Fall 180 % besser als das Zeug, was irgendwie noch in der Mühle war. (War am WE weg, hatte vorher noch Reste vermahlen für die Herdkanne in der Ferienwohnung.) Heute morgen meckerte sogar die Liebste. Bohnen weggeschmissen, wieder die zweiten 500 Gramm des Pascucci eingefüllt - wiederkannt und freudig begrüßt. Wieder kaufen: Nein, aber nur weil er mit 28 Euro inklusive Versand zu teuer ist. Wer in HH wohnt, kriegt ihn für deutlich weniger, dann ist es ein anderes Thema. Aber der Kostenanteil für den Versand ist mir dann im Verhältnis zu hoch. Für fast 30 Euro ist er mir aber nicht Offenbarung genug.",
        "Name": "Pascucci Classic",
        "Packungsgröße": "1000 Gramm",
        "Maschine": "Anfim Best/Domobar",
        "Gekauft am": "Anfang Mai",
        "MHD": "30. September 09, geröstet laut deutschem Vertrieb Ende März 08",
        "Eigenschaften": "Einstellung des Mahlgrads stabil. Einmal gefunden, änderts sich scheinbar nicht so viel. Zum glück, bin ja faul. Habe ihn gekauft, weil er bei espressosorten.de zu den Lieblingen für Cappuccino zählt. Er kommt wirklich dick raus aus dem Auslauf. So dick, dass ich immer denke, er kommt zu schnell raus, aber die Parameter sind soweit okay. (Ich stoppe gelegentlich und schaue auf die Füllmenge. Exakt nachmessen ist nicht meine Welt). Ich finde ihn recht fruchtarm. Im Cappuccino setzt er sich prima durch wie versprochen. Er bleibt dort für meinen  recht - hm - ja, reduziert aufs Geröstete. Dunkel. Kein Schoko, Nuss oder ähnliches. Auf jeden Fall 180 % besser als das Zeug, was irgendwie noch in der Mühle war. (War am WE weg, hatte vorher noch Reste vermahlen für die Herdkanne in der Ferienwohnung.) Heute morgen meckerte sogar die Liebste. Bohnen weggeschmissen, wieder die zweiten 500 Gramm des Pascucci eingefüllt - wiederkannt und freudig begrüßt.",
        "Geschmack": "",
        "Wiederkaufen": "Nein, aber nur weil er mit 28 Euro inklusive Versand zu teuer ist. Wer in HH wohnt, kriegt ihn für deutlich weniger, dann ist es ein anderes Thema. Aber der Kostenanteil für den Versand ist mir dann im Verhältnis zu hoch. Für fast 30 Euro ist er mir aber nicht Offenbarung genug."
    },
    {
        "Full Post": "AW: Ich trinke gerade diesen Espresso.... Name der Bohne: Omkafe Super Bar Packungsgröße: 1000 Gramm Gemahlen und Bezogen mit: Ascaso i-mini / Lelit PL51 (PID/tuned) Gekauft am: 15.05.2008 MHD: - (nicht aufgedruckt, der Kaffee wurde mir von Herrn Martinelli direkt von der Verpackungsmaschine geholt :mrgreen Eigenschaften: Unkompliziert, ausgewogene Mischung, recht kräftig mit langem Nachgeschmack. Dabei kein bischen bitter oder sauer, die angepriesenen 21 Minuten Röstdauer zahlen sich da wohl aus. Gute, stabile Crema in normaler Menge. Vielleicht der beste Kaffee, den ich bisher hatte. Hervorragend pur, aber auch durchsetzungsstark im Cappuccino. Sehr gleichmäßige Röstung ohne verbrannte Stellen oder Abplatzer. Von der Röstqualität kann da von den mir bekannten Röstern nur Mirella mithalten. Nicht ganz billig mit 22 EUR/Kg direkt vom Röster. Wieder kaufen: Wenn ich wieder zum Gardasee komme, auf jeden Fall. Über Versand vielleicht, wenn er nicht zu alt ist. Gruß, Thomas",
        "Name": "Omkafe Super Bar",
        "Packungsgröße": "1000 Gramm",
        "Maschine": "Ascaso i-mini / Lelit PL51 (PID/tuned)",
        "Gekauft am": "15.05.2008",
        "MHD": "- (nicht aufgedruckt, der Kaffee wurde mir von Herrn Martinelli direkt von der Verpackungsmaschine geholt :mrgreen",
        "Eigenschaften": "Unkompliziert, ausgewogene Mischung, recht kräftig mit langem Nachgeschmack. Dabei kein bischen bitter oder sauer, die angepriesenen 21 Minuten Röstdauer zahlen sich da wohl aus. Gute, stabile Crema in normaler Menge. Vielleicht der beste Kaffee, den ich bisher hatte. Hervorragend pur, aber auch durchsetzungsstark im Cappuccino. Sehr gleichmäßige Röstung ohne verbrannte Stellen oder Abplatzer. Von der Röstqualität kann da von den mir bekannten Röstern nur Mirella mithalten. Nicht ganz billig mit 22 EUR/Kg direkt vom Röster.",
        "Geschmack": "",
        "Wiederkaufen": "Wenn ich wieder zum Gardasee komme, auf jeden Fall. Über Versand vielleicht, wenn er nicht zu alt ist. Gruß, Thomas"
    },
    {
        "Full Post": "liebe gemeinde, in einem von mir einst häufig besuchten forum rund um das thema musik war einer der erfolgreichsten threads, der nichts weiter tat, als abzufragen, was die leute gerade hören. nicht gestern, nicht morgen. zu diesem zeitpunkt. das könnte doch auch hier ganz hilfreich sein und neben den anderen seiten im netz, die sich mit einer sortenübersicht beschäftigen, eine übersicht bringen, die von vielen leuten zusammengetragen wird. so ergeben sich zwangsläufig perpektiven, die ein autor allein nicht haben wird. so ähnlich wie die erfahrungsberichte. ich schlage als vor nach folgendem muster vorzugehen: Name der Bohne: Mocambo Oro Packungsgröße: 1000 Gramm Gemahlen und Bezogen mit: Anfim Best/Vibiemme Domobar Gekauft am: Mitte April MHD: 11/09 Eigenschaften: (hier tue ich mich gerade etwas schwer, da ich ihn sehr unterschiedlich finde und nichtmal sicher, ob ich nochmal kaufen würde. aber ich versuch's mal) Bohnen dunkel geröstet, Einstellung des Mahlgrads nach 200 Gramm Rumprobieren recht stabil. Sehr dunkle Schokoladearomen mit nur wenig Frucht, wenig säure. Crema stabil aber trotz sämigen Auslaufs recht flüssiger Espresso. Im Cappuccino kräftig und die fehlende Fruchtigkeit könnte ich jetzt fast vermissen. (genug prosa) Wieder kaufen: Eher nein. so, das wäre so ein muster. aber ich würde vorschlagen, AUSSCHLIESSLICH bohnen zu beschreiben, die wirklich dieser tage in der mühle sind. dafür gerne auch im wochenrhythmus immer die gleiche, falls sich veränderungen von packung zu packung ergeben. nachtrag: vermutlich wäre es sinnvoll, noch das mischungsverhältnis aus arabica und robusta beizuschreiben, vielleicht direkt hinter den namen. so man es denn weiß, ich weiß es beim mocambo nicht und will es auch nicht irgendwo einfach abschreiben.",
        "Name": "Mocambo Oro",
        "Packungsgröße": "1000 Gramm",
        "Maschine": "Anfim Best/Vibiemme Domobar",
        "Gekauft am": "Mitte April",
        "MHD": "11/09",
        "Eigenschaften": "(hier tue ich mich gerade etwas schwer, da ich ihn sehr unterschiedlich finde und nichtmal sicher, ob ich nochmal kaufen würde. aber ich versuch's mal) Bohnen dunkel geröstet, Einstellung des Mahlgrads nach 200 Gramm Rumprobieren recht stabil. Sehr dunkle Schokoladearomen mit nur wenig Frucht, wenig säure. Crema stabil aber trotz sämigen Auslaufs recht flüssiger Espresso. Im Cappuccino kräftig und die fehlende Fruchtigkeit könnte ich jetzt fast vermissen. (genug prosa)",
        "Geschmack": "",
        "Wiederkaufen": "Eher nein. so, das wäre so ein muster. aber ich würde vorschlagen, AUSSCHLIESSLICH bohnen zu beschreiben, die wirklich dieser tage in der mühle sind. dafür gerne auch im wochenrhythmus immer die gleiche, falls sich veränderungen von packung zu packung ergeben. nachtrag: vermutlich wäre es sinnvoll, noch das mischungsverhältnis aus arabica und robusta beizuschreiben, vielleicht direkt hinter den namen. so man es denn weiß, ich weiß es beim mocambo nicht und will es auch nicht irgendwo einfach abschreiben."
    },
    {
        "Full Post": "AW: Ich trinke gerade diesen Espresso.... Name der Bohne: Fausto Giasing Packungsgröße: 500 Gramm Gemahlen und Bezogen mit: Lux/Oscar Gekauft am: Anfang Mai MHD: 05/09 Eigenschaften: Einstellung des Mahlgrads nach 20 g sehr stabil. Fruchtig \"aprikosig\", sehr mild, kräftiger bei etwas mehr Temperatur. Crema gut. Gleicher Eindruck im Cappuccino. Sehr unkomplizierter Kaffee. Wieder kaufen: Ja. Gruss Plempel",
        "Name": "Fausto Giasing",
        "Packungsgröße": "500 Gramm",
        "Maschine": "Lux/Oscar",
        "Gekauft am": "Anfang Mai",
        "MHD": "05/09",
        "Eigenschaften": "Einstellung des Mahlgrads nach 20 g sehr stabil. Fruchtig \"aprikosig\", sehr mild, kräftiger bei etwas mehr Temperatur. Crema gut. Gleicher Eindruck im Cappuccino. Sehr unkomplizierter Kaffee.",
        "Geschmack": "",
        "Wiederkaufen": "Ja. Gruss Plempel"
    },
    {
        "Full Post": "AW: Ich trinke gerade diesen Espresso.... Name der Bohne: Mocambo Oro Packungsgröße: 1000 Gramm Gemahlen und Bezogen mit: Anfim Best/Vibiemme Domobar Gekauft am: Mitte April MHD: 11/09 Eigenschaften: tja, muss vielleicht nochmal neu schreiben. gerade eben mit mehr druck getampert. ziemlich amtliche eckdaten: 25 sec für 60 ml (doppio) aus dem zweierauslauf. schokolade. dunkle, dunkle schokolade (mit zucker getrunken). lang anhaltend im mund, nennen wir es ruhig finish. sehr stabile crema, immer noch kaum säure, mildeste fruchtigkeit. ich merk schon: hartes business, espresso zu verkosten. Wieder kaufen: Eher nein. Nun mit dem Zusatz, dass er mir zu divenhaft ist, da ich schöne ergebnisse auch schon mit weniger Hingabe erzielt habe.",
        "Name": "Mocambo Oro",
        "Packungsgröße": "1000 Gramm",
        "Maschine": "Anfim Best/Vibiemme Domobar",
        "Gekauft am": "Mitte April",
        "MHD": "11/09",
        "Eigenschaften": "tja, muss vielleicht nochmal neu schreiben. gerade eben mit mehr druck getampert. ziemlich amtliche eckdaten: 25 sec für 60 ml (doppio) aus dem zweierauslauf. schokolade. dunkle, dunkle schokolade (mit zucker getrunken). lang anhaltend im mund, nennen wir es ruhig finish. sehr stabile crema, immer noch kaum säure, mildeste fruchtigkeit. ich merk schon: hartes business, espresso zu verkosten.",
        "Geschmack": "",
        "Wiederkaufen": "Eher nein. Nun mit dem Zusatz, dass er mir zu divenhaft ist, da ich schöne ergebnisse auch schon mit weniger Hingabe erzielt habe."
    },
    {
        "Full Post": "AW: Ich trinke gerade diesen Espresso.... Name der Bohne: Mozia von Walter Packungsgröße: 500 Gramm Gemahlen und Bezogen mit: Mazzer Mini E und ner Butterfly Gekauft am: am 3.5 gröstet MHD: Eigenschaften: Hatte ja schon so einige von Walter in der Mazzer, aber dieser ist die beste Mischung die ich bisher von Ihm. Möchte zur Zeit gar keinen Cappu mehr trinken, obwohl meine Frau sagt er wär s** lecker! Sehr Schokolastig mit einer sehr feinen aber dennoch stets präsenten Säure. Sehr rund. Mag eigentlich immer viel Zucker, nehme aber beim Mozia eher weniger! Sehr unkomplizierter Kaffee. Wieder kaufen: Auf jeden Fall! LG Dominik",
        "Name": "Mozia von Walter",
        "Packungsgröße": "500 Gramm",
        "Maschine": "Mazzer Mini E und ner Butterfly",
        "Gekauft am": "am 3.5 gröstet",
        "MHD": ": Hatte ja schon so einige von Walter in der Mazzer, aber dieser ist die beste Mischung die ich bisher von Ihm. Möchte zur Zeit gar keinen Cappu mehr trinken, obwohl meine Frau sagt er wär s** lecker! Sehr Schokolastig mit einer sehr feinen aber dennoch stets präsenten Säure. Sehr rund. Mag eigentlich immer viel Zucker, nehme aber beim Mozia eher weniger! Sehr unkomplizierter Kaffee.",
        "Eigenschaften": "Hatte ja schon so einige von Walter in der Mazzer, aber dieser ist die beste Mischung die ich bisher von Ihm. Möchte zur Zeit gar keinen Cappu mehr trinken, obwohl meine Frau sagt er wär s** lecker! Sehr Schokolastig mit einer sehr feinen aber dennoch stets präsenten Säure. Sehr rund. Mag eigentlich immer viel Zucker, nehme aber beim Mozia eher weniger! Sehr unkomplizierter Kaffee.",
        "Geschmack": "",
        "Wiederkaufen": "Auf jeden Fall! LG Dominik"
    },
    {
        "Full Post": "AW: Ich trinke gerade diesen Espresso.... Name der Bohne: Kaffee vom Schneid, Espresso Pinoro Packungsgröße: 500 Gramm Gemahlen und Bezogen mit: Lux/Oscar Gekauft am: Mitte Mai MHD: vor Ort frisch eingetütet Eigenschaften: Einstellung des Mahlgrads unkompliziert. Bei \"normaler\" Temperatur recht unspektakulär (nicht abwertend gemeint). Ohne, bzw. mit kurzem Leerbezug geht's dann schon zur Sache: Wild, eine Mischung aus Herdkanne und Autobahnraststätte. Crema gut. Verliert sich ein bisschen im Cappuccino. Sehr \"eigener\" Kaffee, love it or leave it. Wieder kaufen: Ja. Gruss Plempel",
        "Name": "Kaffee vom Schneid, Espresso Pinoro",
        "Packungsgröße": "500 Gramm",
        "Maschine": "Lux/Oscar",
        "Gekauft am": "Mitte Mai",
        "MHD": "vor Ort frisch eingetütet",
        "Eigenschaften": "Einstellung des Mahlgrads unkompliziert. Bei \"normaler\" Temperatur recht unspektakulär (nicht abwertend gemeint). Ohne, bzw. mit kurzem Leerbezug geht's dann schon zur Sache: Wild, eine Mischung aus Herdkanne und Autobahnraststätte. Crema gut. Verliert sich ein bisschen im Cappuccino. Sehr \"eigener\" Kaffee, love it or leave it.",
        "Geschmack": "",
        "Wiederkaufen": "Ja. Gruss Plempel"
    },
    {
        "Full Post": "AW: Ich trinke gerade diesen Espresso.... Name der Bohne: Pascucci Classic Packungsgröße: 1000 Gramm Gemahlen und Bezogen mit: Anfim Best/Domobar Gekauft am: Anfang Mai MHD: 30. September 09, geröstet laut deutschem Vertrieb Ende März 08 Eigenschaften: Einstellung des Mahlgrads stabil. Einmal gefunden, änderts sich scheinbar nicht so viel. Zum glück, bin ja faul. Habe ihn gekauft, weil er bei espressosorten.de zu den Lieblingen für Cappuccino zählt. Er kommt wirklich dick raus aus dem Auslauf. So dick, dass ich immer denke, er kommt zu schnell raus, aber die Parameter sind soweit okay. (Ich stoppe gelegentlich und schaue auf die Füllmenge. Exakt nachmessen ist nicht meine Welt). Ich finde ihn recht fruchtarm. Im Cappuccino setzt er sich prima durch wie versprochen. Er bleibt dort für meinen Geschmack recht - hm - ja, reduziert aufs Geröstete. Dunkel. Kein Schoko, Nuss oder ähnliches. Auf jeden Fall 180 % besser als das Zeug, was irgendwie noch in der Mühle war. (War am WE weg, hatte vorher noch Reste vermahlen für die Herdkanne in der Ferienwohnung.) Heute morgen meckerte sogar die Liebste. Bohnen weggeschmissen, wieder die zweiten 500 Gramm des Pascucci eingefüllt - wiederkannt und freudig begrüßt. Wieder kaufen: Nein, aber nur weil er mit 28 Euro inklusive Versand zu teuer ist. Wer in HH wohnt, kriegt ihn für deutlich weniger, dann ist es ein anderes Thema. Aber der Kostenanteil für den Versand ist mir dann im Verhältnis zu hoch. Für fast 30 Euro ist er mir aber nicht Offenbarung genug.",
        "Name": "Pascucci Classic",
        "Packungsgröße": "1000 Gramm",
        "Maschine": "Anfim Best/Domobar",
        "Gekauft am": "Anfang Mai",
        "MHD": "30. September 09, geröstet laut deutschem Vertrieb Ende März 08",
        "Eigenschaften": "Einstellung des Mahlgrads stabil. Einmal gefunden, änderts sich scheinbar nicht so viel. Zum glück, bin ja faul. Habe ihn gekauft, weil er bei espressosorten.de zu den Lieblingen für Cappuccino zählt. Er kommt wirklich dick raus aus dem Auslauf. So dick, dass ich immer denke, er kommt zu schnell raus, aber die Parameter sind soweit okay. (Ich stoppe gelegentlich und schaue auf die Füllmenge. Exakt nachmessen ist nicht meine Welt). Ich finde ihn recht fruchtarm. Im Cappuccino setzt er sich prima durch wie versprochen. Er bleibt dort für meinen  recht - hm - ja, reduziert aufs Geröstete. Dunkel. Kein Schoko, Nuss oder ähnliches. Auf jeden Fall 180 % besser als das Zeug, was irgendwie noch in der Mühle war. (War am WE weg, hatte vorher noch Reste vermahlen für die Herdkanne in der Ferienwohnung.) Heute morgen meckerte sogar die Liebste. Bohnen weggeschmissen, wieder die zweiten 500 Gramm des Pascucci eingefüllt - wiederkannt und freudig begrüßt.",
        "Geschmack": "",
        "Wiederkaufen": "Nein, aber nur weil er mit 28 Euro inklusive Versand zu teuer ist. Wer in HH wohnt, kriegt ihn für deutlich weniger, dann ist es ein anderes Thema. Aber der Kostenanteil für den Versand ist mir dann im Verhältnis zu hoch. Für fast 30 Euro ist er mir aber nicht Offenbarung genug."
    },
    {
        "Full Post": "AW: Ich trinke gerade diesen Espresso.... Name der Bohne: Omkafe Super Bar Packungsgröße: 1000 Gramm Gemahlen und Bezogen mit: Ascaso i-mini / Lelit PL51 (PID/tuned) Gekauft am: 15.05.2008 MHD: - (nicht aufgedruckt, der Kaffee wurde mir von Herrn Martinelli direkt von der Verpackungsmaschine geholt :mrgreen Eigenschaften: Unkompliziert, ausgewogene Mischung, recht kräftig mit langem Nachgeschmack. Dabei kein bischen bitter oder sauer, die angepriesenen 21 Minuten Röstdauer zahlen sich da wohl aus. Gute, stabile Crema in normaler Menge. Vielleicht der beste Kaffee, den ich bisher hatte. Hervorragend pur, aber auch durchsetzungsstark im Cappuccino. Sehr gleichmäßige Röstung ohne verbrannte Stellen oder Abplatzer. Von der Röstqualität kann da von den mir bekannten Röstern nur Mirella mithalten. Nicht ganz billig mit 22 EUR/Kg direkt vom Röster. Wieder kaufen: Wenn ich wieder zum Gardasee komme, auf jeden Fall. Über Versand vielleicht, wenn er nicht zu alt ist. Gruß, Thomas",
        "Name": "Omkafe Super Bar",
        "Packungsgröße": "1000 Gramm",
        "Maschine": "Ascaso i-mini / Lelit PL51 (PID/tuned)",
        "Gekauft am": "15.05.2008",
        "MHD": "- (nicht aufgedruckt, der Kaffee wurde mir von Herrn Martinelli direkt von der Verpackungsmaschine geholt :mrgreen",
        "Eigenschaften": "Unkompliziert, ausgewogene Mischung, recht kräftig mit langem Nachgeschmack. Dabei kein bischen bitter oder sauer, die angepriesenen 21 Minuten Röstdauer zahlen sich da wohl aus. Gute, stabile Crema in normaler Menge. Vielleicht der beste Kaffee, den ich bisher hatte. Hervorragend pur, aber auch durchsetzungsstark im Cappuccino. Sehr gleichmäßige Röstung ohne verbrannte Stellen oder Abplatzer. Von der Röstqualität kann da von den mir bekannten Röstern nur Mirella mithalten. Nicht ganz billig mit 22 EUR/Kg direkt vom Röster.",
        "Geschmack": "",
        "Wiederkaufen": "Wenn ich wieder zum Gardasee komme, auf jeden Fall. Über Versand vielleicht, wenn er nicht zu alt ist. Gruß, Thomas"
    },
    {
        "Full Post": "AW: Ich trinke gerade diesen Espresso.... Name der Bohne: Caffe Vergnano Gran Aroma Bar Packungsgröße: 1000 Gramm Gemahlen und Bezogen mit: Lux/Oscar Gekauft am: Anfang Juni 08 MHD: 05/10 Eigenschaften: Einstellung des Mahlgrads problemlos. Bisschen malzig, riecht besser als er schmeckt. Wird auch mit viel Zucker nicht trinkbarer. Zwischen sauer und bitter ist der ausgewogene Geschmacksbereich sehr eng und (für mich) schwer zu treffen. Crema gut. Als Cappuccino ganz erträglich. Sehr \"eigener\" Kaffee. Wieder kaufen: Nein. Gruss Plempel",
        "Name": "Caffe Vergnano Gran Aroma Bar",
        "Packungsgröße": "1000 Gramm",
        "Maschine": "Lux/Oscar",
        "Gekauft am": "Anfang Juni 08",
        "MHD": "05/10",
        "Eigenschaften": "Einstellung des Mahlgrads problemlos. Bisschen malzig, riecht besser als er schmeckt. Wird auch mit viel Zucker nicht trinkbarer. Zwischen sauer und bitter ist der ausgewogene sbereich sehr eng und (für mich) schwer zu treffen. Crema gut. Als Cappuccino ganz erträglich. Sehr \"eigener\" Kaffee.",
        "Geschmack": "",
        "Wiederkaufen": "Nein. Gruss Plempel"
    },
    {
        "Full Post": "AW: Ich trinke gerade diesen Espresso.... Name der Bohne: Langen Classico Packungsgröße: 500 Gramm Gemahlen und Bezogen mit: Anfim/Domobar Gekauft am: 04.06.08 MHD: 03.06.09 Eigenschaften: Meine Frau sagte heute morgen ohne vom Bohnenwechsel von gestern zu wissen: \"Der Cappuccino schmeckt aber gut heute.\" Do I need to say more???? Eine Stufe gröber als der Fuerte gemahlen. Vielleicht weniger schokoladig als der Fuerte. Aber kräftig und gut. Als Espresso muss ich ihn noch testen heute abend. So, gerade geschehen. Kräftige Bittertöne, die man mögen muss, mir aber noch gut in den Kram passen. Leichte Säure, die ich üblicherweise auch nicht so schätze und folgerichtig als Espresso den Fuerte dem Classico vorziehe. Im Cappuccino hingegen machte er sich ja wie gesagt hervorragend. Als Espresso auch - nicht falsch verstehen. Harmonisch, Schokolade (wenn auch noch dunklere), unaufdringliche Säure. NACHTRAG: Ich meine, dass der Classico als recht dünner Strahl herauskommt. Ich mag nicht glauben, dass es mit der Frische zu tun haben kann. Unmöglich, er ist viel zu frisch, keine drei Wochen alt. Ob es typisch für ihn ist, vielleicht doch meine Temperatur nicht in Ordnung ist, keine Ahnung. Wie gesagt, er ist prima, so wie er ist und dann akzeptiere ich mal, dass nicht jeder armdick rauskommen kann. Hatte ich schonmal bei Mocambo, meine ich. Wieder kaufen: If the lady likes it....",
        "Name": "Langen Classico",
        "Packungsgröße": "500 Gramm",
        "Maschine": "Anfim/Domobar",
        "Gekauft am": "04.06.08",
        "MHD": "03.06.09",
        "Eigenschaften": "Meine Frau sagte heute morgen ohne vom Bohnenwechsel von gestern zu wissen: \"Der Cappuccino schmeckt aber gut heute.\" Do I need to say more???? Eine Stufe gröber als der Fuerte gemahlen. Vielleicht weniger schokoladig als der Fuerte. Aber kräftig und gut. Als Espresso muss ich ihn noch testen heute abend. So, gerade geschehen. Kräftige Bittertöne, die man mögen muss, mir aber noch gut in den Kram passen. Leichte Säure, die ich üblicherweise auch nicht so schätze und folgerichtig als Espresso den Fuerte dem Classico vorziehe. Im Cappuccino hingegen machte er sich ja wie gesagt hervorragend. Als Espresso auch - nicht falsch verstehen. Harmonisch, Schokolade (wenn auch noch dunklere), unaufdringliche Säure. NACHTRAG: Ich meine, dass der Classico als recht dünner Strahl herauskommt. Ich mag nicht glauben, dass es mit der Frische zu tun haben kann. Unmöglich, er ist viel zu frisch, keine drei Wochen alt. Ob es typisch für ihn ist, vielleicht doch meine Temperatur nicht in Ordnung ist, keine Ahnung. Wie gesagt, er ist prima, so wie er ist und dann akzeptiere ich mal, dass nicht jeder armdick rauskommen kann. Hatte ich schonmal bei Mocambo, meine ich.",
        "Geschmack": "",
        "Wiederkaufen": "If the lady likes it...."
    },
    {
        "Full Post": "AW: Ich trinke gerade diesen Espresso.... Name der Bohne: Caffe Mas Rosso Packungsgröße: 1000 Gramm Gemahlen und Bezogen mit: Lux/Oscar Gekauft am: Mitte Juli MHD: 05/10 Eigenschaften: 90% Robusta, war etwas gespannt, wie das wird. Aber mit nicht zu feinem Mahlgrad und einem schön langen Leerbezug wird ein richtig guter Espresso draus. Nicht spektakulär, ohne auffallende \"Geschmacksrichtung\", nicht bitter, einfach rund. Schmeckt viel besser als er riecht. Frau Plempel meinte sogar, es wäre der beste Cappu, den sie seit langer Zeit getrunken habe. (\"Mmmmh, ist der leeeecker...\") :-? Sehr unkomplizierter Kaffee. Absoluter Tipp im Low-Budget Bereich (10,-/Kilo) Wieder kaufen: Ja. Wenn er wieder relativ frisch hergeht. Muss auch noch den silbernen und den goldenen probieren. Gruss Plempel",
        "Name": "Caffe Mas Rosso",
        "Packungsgröße": "1000 Gramm",
        "Maschine": "Lux/Oscar",
        "Gekauft am": "Mitte Juli",
        "MHD": "05/10",
        "Eigenschaften": "90% Robusta, war etwas gespannt, wie das wird. Aber mit nicht zu feinem Mahlgrad und einem schön langen Leerbezug wird ein richtig guter Espresso draus. Nicht spektakulär, ohne auffallende \"srichtung\", nicht bitter, einfach rund. Schmeckt viel besser als er riecht. Frau Plempel meinte sogar, es wäre der beste Cappu, den sie seit langer Zeit getrunken habe. (\"Mmmmh, ist der leeeecker...\") :-? Sehr unkomplizierter Kaffee. Absoluter Tipp im Low-Budget Bereich (10,-/Kilo)",
        "Geschmack": "",
        "Wiederkaufen": "Ja. Wenn er wieder relativ frisch hergeht. Muss auch noch den silbernen und den goldenen probieren. Gruss Plempel"
    },
    {
        "Full Post": "AW: Ich trinke gerade diesen Espresso.... Name der Bohne: Ionia Linea Bar Packungsgröße: 1000 Gramm Gemahlen und Bezogen mit: BZ99 / Cunil Tauro Gekauft am: Anfang Juli MHD: 03/10 Eigenschaften: die Bohnen haben geschätze 40% Robustaanteil. Ich musste die Mühle deutlich grober stellen. Nachdem ich von dem doch recht feinen Espresso Dulce der Kettwiger Rösterei auf den Ionia Linea Bar umgestiegen bin, war das als ob einem jemand nen Schlag mit dem Dampfhammer verpasst. Nachdem die Bohnen nun aber ein paar Tage offen sind, ist der Geschmack etwas weicher und deutlich trinkbarer geworden. Nun hat man einen echten rauchigen süditalienischen Bar-Espresso ohne Säure aber mit ordentlich Dampf, der auch eine ordentliche Portion Zucker verträgt (trinke Espresso sonst meist ohne Zucker). Die Handhabung ist sehr unkompliziert, das Ergebnis ist immer ähnlich gut und man hat eine ordentliche Crema. Im Cappu ist er ebenfalls nicht schlecht, da er nicht in der Milch untergeht und seinen Charakter behält. Wieder kaufen: für 10€/Kg ist er ein interessanter Espresso, aber ich würde wohl eher wieder zum Ionia Gran Crema tendieren...",
        "Name": "Ionia Linea Bar",
        "Packungsgröße": "1000 Gramm",
        "Maschine": "BZ99 / Cunil Tauro",
        "Gekauft am": "Anfang Juli",
        "MHD": "03/10",
        "Eigenschaften": "die Bohnen haben geschätze 40% Robustaanteil. Ich musste die Mühle deutlich grober stellen. Nachdem ich von dem doch recht feinen Espresso Dulce der Kettwiger Rösterei auf den Ionia Linea Bar umgestiegen bin, war das als ob einem jemand nen Schlag mit dem Dampfhammer verpasst. Nachdem die Bohnen nun aber ein paar Tage offen sind, ist der  etwas weicher und deutlich trinkbarer geworden. Nun hat man einen echten rauchigen süditalienischen Bar-Espresso ohne Säure aber mit ordentlich Dampf, der auch eine ordentliche Portion Zucker verträgt (trinke Espresso sonst meist ohne Zucker). Die Handhabung ist sehr unkompliziert, das Ergebnis ist immer ähnlich gut und man hat eine ordentliche Crema. Im Cappu ist er ebenfalls nicht schlecht, da er nicht in der Milch untergeht und seinen Charakter behält.",
        "Geschmack": "",
        "Wiederkaufen": "für 10€/Kg ist er ein interessanter Espresso, aber ich würde wohl eher wieder zum Ionia Gran Crema tendieren..."
    },
    {
        "Full Post": "AW: Ich trinke gerade diesen Espresso.... Name der Bohne: Zicaffe Gusto Rosso Packungsgröße: 1000 Gramm Gemahlen und Bezogen mit: Lux/Oscar Gekauft: August (ok, nicht wirklich gekauft) MHD: 06/10 Eigenschaften: Braucht feine Mahlung und (bei meiner Oscar) sorgfältiges Verteilen/Tampen, schönen Leerbezug. \"Schokoladig - Fruchtig - Gut\" (sagt Frau Plempel :roll. Riecht sehr gut. Guter \"Barbrecher\", Crema gut. Super Eindruck im Cappuccino, wäre mein Lieblings-Cappu-Kaffee, wenn ich zwei Mühlen hätte. :-? Wieder kaufen: Ja. Gruss Plempel",
        "Name": "Zicaffe Gusto Rosso",
        "Packungsgröße": "1000 Gramm",
        "Maschine": "Lux/Oscar Gekauft: August (ok, nicht wirklich gekauft)",
        "Gekauft am": "",
        "MHD": "06/10",
        "Eigenschaften": "Braucht feine Mahlung und (bei meiner Oscar) sorgfältiges Verteilen/Tampen, schönen Leerbezug. \"Schokoladig - Fruchtig - Gut\" (sagt Frau Plempel :roll. Riecht sehr gut. Guter \"Barbrecher\", Crema gut. Super Eindruck im Cappuccino, wäre mein Lieblings-Cappu-Kaffee, wenn ich zwei Mühlen hätte. :-?",
        "Geschmack": "",
        "Wiederkaufen": "Ja. Gruss Plempel"
    },
    {
        "Full Post": "AW: Ich trinke gerade diesen Espresso.... Name der Bohne: Riviera Miscela C. Colombo Packungsgröße: 1000 Gramm Gemahlen und Bezogen mit: Lux/Oscar Gekauft: August, Spina MHD: 06/10 Eigenschaften: Braucht feine Mahlung und rel. wenig Kaffee (14-15/8 Gramm), sonst wird er schnell streng/bitter (bei meiner Oscar). Angenehme Säure, Crema gut. Guter Allrounder, eher unauffällig. Eine gute Wahl wenn man von den \"aufdringlichen\" Kaffees mal eine Pause braucht. Wieder kaufen: Durchaus. Gruss Plempel",
        "Name": "Riviera Miscela C. Colombo",
        "Packungsgröße": "1000 Gramm",
        "Maschine": "Lux/Oscar Gekauft: August, Spina",
        "Gekauft am": "",
        "MHD": "06/10",
        "Eigenschaften": "Braucht feine Mahlung und rel. wenig Kaffee (14-15/8 Gramm), sonst wird er schnell streng/bitter (bei meiner Oscar). Angenehme Säure, Crema gut. Guter Allrounder, eher unauffällig. Eine gute Wahl wenn man von den \"aufdringlichen\" Kaffees mal eine Pause braucht.",
        "Geschmack": "",
        "Wiederkaufen": "Durchaus. Gruss Plempel"
    },
    {
        "Full Post": "AW: Ich trinke gerade diesen Espresso.... Name der Bohne: MokaMO forte (70/30) Packungsgröße: 1000 Gramm Gemahlen und Bezogen mit: Siemens TC 55002 (baugleich Saeco stratos) Gekauft am: Mitte Juli MHD: Verpackung nicht mehr vorhanden Eigenschaften: Bohnen mittelhell. Nachdem ich die Mengeneinstellung in die Mittelposition gestellt habe, war gleich die zweite Tasse sehr lecker. Leichte, recht stabile Crema, würzig und kräftig. Keine Bitterstoffe und nur eine sehr, sehr leichte Säure zu schmecken. Ob als \"Kaffee lang\", Espresso oder Cappucino, der MokaMO forte hinterläßt immer einen kräftig-positiven Eindruck. Wieder kaufen: Sofort! Hoffentlich könnt Ihr mit meinen laienhaften Eindrücken was anfangen. Zum Cappucino-Trinker werde ich nur im Büro, daheim gibts Darjeeling :lol:",
        "Name": "MokaMO forte (70/30)",
        "Packungsgröße": "1000 Gramm",
        "Maschine": "Siemens TC 55002 (baugleich Saeco stratos)",
        "Gekauft am": "Mitte Juli",
        "MHD": "Verpackung nicht mehr vorhanden",
        "Eigenschaften": "Bohnen mittelhell. Nachdem ich die Mengeneinstellung in die Mittelposition gestellt habe, war gleich die zweite Tasse sehr lecker. Leichte, recht stabile Crema, würzig und kräftig. Keine Bitterstoffe und nur eine sehr, sehr leichte Säure zu schmecken. Ob als \"Kaffee lang\", Espresso oder Cappucino, der MokaMO forte hinterläßt immer einen kräftig-positiven Eindruck.",
        "Geschmack": "",
        "Wiederkaufen": "Sofort! Hoffentlich könnt Ihr mit meinen laienhaften Eindrücken was anfangen. Zum Cappucino-Trinker werde ich nur im Büro, daheim gibts Darjeeling :lol:"
    },
    {
        "Full Post": "AW: Ich trinke gerade diesen Espresso.... Name der Bohne: Lucaffe Espresso Bar Packungsgröße: 1000 Gramm/ 18,70 Euro (glaube ich) , direkt ab Röster Gemahlen und Bezogen mit: BZ 99 /Mazzer Mini E Gekauft am: 10.09.2008 MHD: 08/2010 Eigenschaften: eine typisch italienische Barmischung (60/40). Ich hab´ jetzt mehr als die Hälfte des Pakets durch und ein Schuß gelingt wie der nächste. Er hat eine starke Crema (wen wunderts bei 40 prozent Robusta) und schmeckt extrem schokoladig bei -0- Säure. Ich vergleiche ihn mit dem Zicaffe Gusto Rosso nur dass er nicht so rauchig, irgendwie feiner schmeckt. Ideal für Anfänger die auf Cremasuche sind. Wieder kaufen: sicher doch, nächsten September wieder am Gardasee",
        "Name": "Lucaffe Espresso Bar",
        "Packungsgröße": "1000 Gramm/ 18,70 Euro (glaube ich) , direkt ab Röster",
        "Maschine": "BZ 99 /Mazzer Mini E",
        "Gekauft am": "10.09.2008",
        "MHD": "08/2010",
        "Eigenschaften": "eine typisch italienische Barmischung (60/40). Ich hab´ jetzt mehr als die Hälfte des Pakets durch und ein Schuß gelingt wie der nächste. Er hat eine starke Crema (wen wunderts bei 40 prozent Robusta) und schmeckt extrem schokoladig bei -0- Säure. Ich vergleiche ihn mit dem Zicaffe Gusto Rosso nur dass er nicht so rauchig, irgendwie feiner schmeckt. Ideal für Anfänger die auf Cremasuche sind.",
        "Geschmack": "",
        "Wiederkaufen": "sicher doch, nächsten September wieder am Gardasee"
    },
    {
        "Full Post": "AW: Ich trinke gerade diesen Espresso.... Name der Bohne: Picada Siena, 100% Arabica Packungsgröße: 500 Gramm Gemahlen und Bezogen mit: Lux/Oscar Gekauft: Mitte September MHD: 09/09 Eigenschaften: Das erste Mal seit einem halben Jahr wieder rrröstfrischen Kaffee gekauft. Muss sagen, hatte den nicht als so zickig in Erinnerung, aber vielleicht bin ich nur verwöhnt von meinen \"unkomplizierten\" Italo-Brechern. Mahlgrad und richtige Menge zu finden war nicht einfach, musste meine Hi-End State of the Art Mühle frisieren, nur um festzustellen, dass es dann doch zu fein war, mal mehr, mal weniger Pulver, zu heiss, zu kalt, bitter, scharf, aggressiv ... Katastrophe! Heute passt es. (zufällig?) Das Ergebnis ist ein wohlschmeckender, nicht bitterer, sehr eigener Kaffee. (so hatte ich ihn auch in Erinnerung) Crema gut, nicht sehr anhaltend, Geruch sehr gut, kommt auch noch im (kleinen) Cappu. Ich glaube, das ist so ein Kaffee, der mir die Grenzen meiner Ausrüstung aufzeigt: Natürlich würde ich gerne besseres Mahlgut haben, die Brühtemperatur besser kontrollieren und den Druck mal reduzieren können, denn so bleiben die Ergebnisse schlecht reproduzierbar. Wenn alles passt, schmeckt's sehr gut, wenn aber nur irgendwas minimal daneben liegt geht's rapide in die Hose. Schade. Wieder kaufen: Ja. Und neue Mühle. Und PID. Und Ventil. und und und... Gruss Plempel",
        "Name": "Picada Siena, 100% Arabica",
        "Packungsgröße": "500 Gramm",
        "Maschine": "Lux/Oscar Gekauft: Mitte September",
        "Gekauft am": "",
        "MHD": "09/09",
        "Eigenschaften": "Das erste Mal seit einem halben Jahr wieder rrröstfrischen Kaffee gekauft. Muss sagen, hatte den nicht als so zickig in Erinnerung, aber vielleicht bin ich nur verwöhnt von meinen \"unkomplizierten\" Italo-Brechern. Mahlgrad und richtige Menge zu finden war nicht einfach, musste meine Hi-End State of the Art Mühle frisieren, nur um festzustellen, dass es dann doch zu fein war, mal mehr, mal weniger Pulver, zu heiss, zu kalt, bitter, scharf, aggressiv ... Katastrophe! Heute passt es. (zufällig?) Das Ergebnis ist ein wohlschmeckender, nicht bitterer, sehr eigener Kaffee. (so hatte ich ihn auch in Erinnerung) Crema gut, nicht sehr anhaltend, Geruch sehr gut, kommt auch noch im (kleinen) Cappu. Ich glaube, das ist so ein Kaffee, der mir die Grenzen meiner Ausrüstung aufzeigt: Natürlich würde ich gerne besseres Mahlgut haben, die Brühtemperatur besser kontrollieren und den Druck mal reduzieren können, denn so bleiben die Ergebnisse schlecht reproduzierbar. Wenn alles passt, schmeckt's sehr gut, wenn aber nur irgendwas minimal daneben liegt geht's rapide in die Hose. Schade.",
        "Geschmack": "",
        "Wiederkaufen": "Ja. Und neue Mühle. Und PID. Und Ventil. und und und... Gruss Plempel"
    },
    {
        "Full Post": "AW: Ich trinke gerade diesen Espresso.... Name der Bohne: Molinari Oro Packungsgröße: 500 Gramm (90/10?) Gemahlen und Bezogen mit: Lux/Oscar Gekauft: November MHD: 06/10 Eigenschaften: Seit langem mal wieder ein Kaffee, den ich nach einigen Tassen \"entsorgt\" habe (d. h. ab ins Büro, VA damit stopfen). Der ist uns einfach zu bitter. Beim Trinken geht's ja noch, aber der Nachgeschmack ... Vielleicht war er nur zu alt oder es ist so ein Ober-Checker-Kaffee, der eine ganz exakte Zubereitung braucht, keine Ahnung. Bin entäuscht. War auch nicht billig (10,-/Pfund; wär ich doch nur 10 Minuten weitergefahren, hätte ich frischen Fausto kaufen können...). Wieder kaufen: Sicher nicht. Gruss Plempel",
        "Name": "Molinari Oro",
        "Packungsgröße": "500 Gramm (90/10?)",
        "Maschine": "Lux/Oscar Gekauft: November",
        "Gekauft am": "",
        "MHD": "06/10",
        "Eigenschaften": "Seit langem mal wieder ein Kaffee, den ich nach einigen Tassen \"entsorgt\" habe (d. h. ab ins Büro, VA damit stopfen). Der ist uns einfach zu bitter. Beim Trinken geht's ja noch, aber der Nachgeschmack ... Vielleicht war er nur zu alt oder es ist so ein Ober-Checker-Kaffee, der eine ganz exakte Zubereitung braucht, keine Ahnung. Bin entäuscht. War auch nicht billig (10,-/Pfund; wär ich doch nur 10 Minuten weitergefahren, hätte ich frischen Fausto kaufen können...).",
        "Geschmack": "",
        "Wiederkaufen": "Sicher nicht. Gruss Plempel"
    },
    {
        "Full Post": "AW: Ich trinke gerade diesen Espresso.... Name der Bohne: Lucaffe Mamma Lucia Packungsgröße: 1000 Gramm (70/30?) Gemahlen und Bezogen mit: Lux/Oscar Gekauft: November MHD: 10/10 Eigenschaften: Weiss nicht, was ich von diesem Kaffee halten soll: Zwar relativ unkompliziert, aber irgendwie harmlos, nicht schlecht, aber auch nicht gut, ist ein wenig bitter, ansonsten kann ich keine Geschmacksnuancen feststellen, auch kein interessanter \"Eigengeschmack\". Im Cappu säuft er total ab. Warte immer noch, ob was kommt, glaube aber nicht. Vielleicht habe ich auch gerade den harmlosesten von Lucaffe erwischt, oder er muss präziser zubereitet werden oder gehört in einen VA, keine Ahnung, bin ein bisschen entäuscht. Wieder kaufen: Nö, muss nicht sein, auch viel zu teuer für das, was unten rauskommt. Gruss Plempel Nachtrag: Wenn ich genauer dosiere (Max 7/14 Gramm) wird's besser. Scheinbar sehr empfindlich für \"überdosierung\". Richtig gut wird er trotzdem nicht.",
        "Name": "Lucaffe Mamma Lucia",
        "Packungsgröße": "1000 Gramm (70/30?)",
        "Maschine": "Lux/Oscar Gekauft: November",
        "Gekauft am": "",
        "MHD": "10/10",
        "Eigenschaften": "Weiss nicht, was ich von diesem Kaffee halten soll: Zwar relativ unkompliziert, aber irgendwie harmlos, nicht schlecht, aber auch nicht gut, ist ein wenig bitter, ansonsten kann ich keine snuancen feststellen, auch kein interessanter \"Eigengeschmack\". Im Cappu säuft er total ab. Warte immer noch, ob was kommt, glaube aber nicht. Vielleicht habe ich auch gerade den harmlosesten von Lucaffe erwischt, oder er muss präziser zubereitet werden oder gehört in einen VA, keine Ahnung, bin ein bisschen entäuscht.",
        "Geschmack": "",
        "Wiederkaufen": "Nö, muss nicht sein, auch viel zu teuer für das, was unten rauskommt. Gruss Plempel Nachtrag: Wenn ich genauer dosiere (Max 7/14 Gramm) wird's besser. Scheinbar sehr empfindlich für \"überdosierung\". Richtig gut wird er trotzdem nicht."
    },
    {
        "Full Post": "AW: Ich trinke gerade diesen Espresso.... Name der Bohne: Mauro Espresso Bar Packungsgröße: 1000 Gramm Gemahlen und Bezogen mit: Gaggia Roma/Gaggia Classic Gekauft am: Mitte November MHD: ??/10 (Beutel schon weggeschmissen) Eigenschaften: Erster Eindruck, als ich den Beutel öffnete: Der stinkt! Von den kleinen, fast schwarzen Bohnen strömte mir ein teerartiger Geruch entgegen. Kann dieser Kaffee wirklich gut sein? Ja, er kann! Das genaue Gegenteil von gewissen Supermarkt-Sorten, die einen herrlichen Kaffeeduft verbreiten, aber es kommt nur sehr wenig davon in die Tasse. Beim Mauro fällt mir eine süssliche Note auf, die an Marzipan oder Kastanien erinnert. Ein gewisser Toast-Geschmack ist auch da. Von den schwarzen Böhnchen hätte ich mehr Wucht erwartet. Keine Kritik, nur eine Feststellung. Ich empfinde ihn auf eine interessante, intensive Art als \"lieblich\". Kaffeegeschmack nicht sehr lang anhaltend, wirkt hinterher eher so, als hätte ich Marzipan gegessen. Recht unproblematisch in der Zubereitung, ziemlich fehlertolerant. Überextraktion mag er nicht, da wird die Süsslichkeit sogar noch überbetont neben einer gewissen Bitterkeit (in punkto Bitterkeit kenne ich schlimmere Sorten!). Mit einer Extraktionszeit von 20-25 Sekunden komme ich zu einem besseren Resultat als bei 25-30 Sekunden. Vielleicht liegt das daran, dass meine Gaggia nicht brühdruckreduziert ist? Üppige Crema. Wieder kaufen: Weiss noch nicht, vielleicht ab und zu. Ein eher \"dunkler\", rassiger Kaffeegeschmack ist mir eben doch lieber. Die Kaffeezentrale schreibt: \"Bald werden Sie andere Sorten nur noch langweilig finden\". Das glaube ich nicht! Gruss Hans",
        "Name": "Mauro Espresso Bar",
        "Packungsgröße": "1000 Gramm",
        "Maschine": "Gaggia Roma/Gaggia Classic",
        "Gekauft am": "Mitte November",
        "MHD": "??/10 (Beutel schon weggeschmissen)",
        "Eigenschaften": "Erster Eindruck, als ich den Beutel öffnete: Der stinkt! Von den kleinen, fast schwarzen Bohnen strömte mir ein teerartiger Geruch entgegen. Kann dieser Kaffee wirklich gut sein? Ja, er kann! Das genaue Gegenteil von gewissen Supermarkt-Sorten, die einen herrlichen Kaffeeduft verbreiten, aber es kommt nur sehr wenig davon in die Tasse. Beim Mauro fällt mir eine süssliche Note auf, die an Marzipan oder Kastanien erinnert. Ein gewisser Toast- ist auch da. Von den schwarzen Böhnchen hätte ich mehr Wucht erwartet. Keine Kritik, nur eine Feststellung. Ich empfinde ihn auf eine interessante, intensive Art als \"lieblich\". Kaffeegeschmack nicht sehr lang anhaltend, wirkt hinterher eher so, als hätte ich Marzipan gegessen. Recht unproblematisch in der Zubereitung, ziemlich fehlertolerant. Überextraktion mag er nicht, da wird die Süsslichkeit sogar noch überbetont neben einer gewissen Bitterkeit (in punkto Bitterkeit kenne ich schlimmere Sorten!). Mit einer Extraktionszeit von 20-25 Sekunden komme ich zu einem besseren Resultat als bei 25-30 Sekunden. Vielleicht liegt das daran, dass meine Gaggia nicht brühdruckreduziert ist? Üppige Crema.",
        "Geschmack": "",
        "Wiederkaufen": "Weiss noch nicht, vielleicht ab und zu. Ein eher \"dunkler\", rassiger Kaffeegeschmack ist mir eben doch lieber. Die Kaffeezentrale schreibt: \"Bald werden Sie andere Sorten nur noch langweilig finden\". Das glaube ich nicht! Gruss Hans"
    },
    {
        "Full Post": "AW: Ich trinke gerade diesen Espresso.... Name der Bohne: Bonomi Macumba Packungsgröße: 1000 Gramm (80/20?) Gemahlen und Bezogen mit: Lux/Oscar Gekauft: Dezember Verpackungsdatum: 10/08 MHD: 04/10 Eigenschaften: Ein (\"Alltags\") Kaffee ganz nach meinem Geschmack: Da muss man nicht lange rumpröbeln, passt ab dem ersten \"Schuss\", bissl Finetuning, fertig. Nicht aufdringlich, lässt Platz für Geschmacksinterpretationen (Spezialdisziplin von Fr. Plempel). Hat ein bisschen was von Amarettini. Der Kaffee. Wieder kaufen: Ja, leider nicht immer so (relativ) frisch auf Lager (was für ein Widerspruch ) Ach ja, ist mit zehnfuffzig fürs Kilo auch noch günstig. Gruss Plempel",
        "Name": "Bonomi Macumba",
        "Packungsgröße": "1000 Gramm (80/20?)",
        "Maschine": "Lux/Oscar Gekauft: Dezember Verpackungsdatum: 10/08",
        "Gekauft am": "",
        "MHD": "04/10",
        "Eigenschaften": "Ein (\"Alltags\") Kaffee ganz nach meinem",
        "Geschmack": "Da muss man nicht lange rumpröbeln, passt ab dem ersten \"Schuss\", bissl Finetuning, fertig. Nicht aufdringlich, lässt Platz für sinterpretationen (Spezialdisziplin von Fr. Plempel). Hat ein bisschen was von Amarettini. Der Kaffee.",
        "Wiederkaufen": "Ja, leider nicht immer so (relativ) frisch auf Lager (was für ein Widerspruch ) Ach ja, ist mit zehnfuffzig fürs Kilo auch noch günstig. Gruss Plempel"
    },
    {
        "Full Post": "AW: Ich trinke gerade diesen Espresso.... Name der Bohne: Blaser Puerto Rico Packungsgröße: 250 Gramm Gemahlen und Bezogen mit: K3 / Perfetta Gekauft: Dezember MHD: 16.05/09 Eigenschaften: Riecht ein wenig süss (Bonbon?). Sehr angenehm. Wirkt sehr wertig. Etwas feiner gemahlen als Passalacqua Harem. Hat bezogen immer noch diesen wertigen süssen Duft. Und schmeckt umwerfend gut. Tritt stark auf, nicht aufdringlich. Sehr ausgewogen und hält lange an. Brennt sehr angenehm nach und das ohne den dafür typischen Schokoflair. Habe sehr viele Sorten bislang ausprobiert. Manche haben mir sehr gut gefallen. Dieser sticht aber heraus. Schon beim ersten Bezug sagt er mir komplett zu. Für mich die Nummer 1 bislang. (Liegt aber auch noch ungeöffnet ein Brasil Corazon und ein Ethiopia Sidamo herum) Wieder kaufen: Ja, ist aber auch erst der Zweite der bei mir auf diese Liste kommt. Langen Tatico ist daneben weil er so unkompliziert solide ist.",
        "Name": "Blaser Puerto Rico",
        "Packungsgröße": "250 Gramm",
        "Maschine": "K3 / Perfetta Gekauft: Dezember",
        "Gekauft am": "",
        "MHD": "16.05/09",
        "Eigenschaften": "Riecht ein wenig süss (Bonbon?). Sehr angenehm. Wirkt sehr wertig. Etwas feiner gemahlen als Passalacqua Harem. Hat bezogen immer noch diesen wertigen süssen Duft. Und schmeckt umwerfend gut. Tritt stark auf, nicht aufdringlich. Sehr ausgewogen und hält lange an. Brennt sehr angenehm nach und das ohne den dafür typischen Schokoflair. Habe sehr viele Sorten bislang ausprobiert. Manche haben mir sehr gut gefallen. Dieser sticht aber heraus. Schon beim ersten Bezug sagt er mir komplett zu. Für mich die Nummer 1 bislang. (Liegt aber auch noch ungeöffnet ein Brasil Corazon und ein Ethiopia Sidamo herum)",
        "Geschmack": "",
        "Wiederkaufen": "Ja, ist aber auch erst der Zweite der bei mir auf diese Liste kommt. Langen Tatico ist daneben weil er so unkompliziert solide ist."
    },
    {
        "Full Post": "AW: Ich trinke gerade diesen Espresso.... Name der Bohne: Tre Forze Packungsgröße: 250 Gramm Gemahlen und Bezogen mit: K3 / Perfetta Gekauft: Dezember MHD: Steht nichts drauf Eigenschaften: Sehr dichte und füllige Crema. Sehr aromatisch und leicht bitter. Gerade so an der Grenze wo es nicht mehr so nett ist. Dadurch sehr interessant. Lässt sich durch herumexperimentieren aber sicher minimieren. Sehr trinkbar. Ist halt sein Charakter. > Tre Forze < Wieder kaufen: Vielleicht",
        "Name": "Tre Forze",
        "Packungsgröße": "250 Gramm",
        "Maschine": "K3 / Perfetta Gekauft: Dezember",
        "Gekauft am": "",
        "MHD": "Steht nichts drauf",
        "Eigenschaften": "Sehr dichte und füllige Crema. Sehr aromatisch und leicht bitter. Gerade so an der Grenze wo es nicht mehr so nett ist. Dadurch sehr interessant. Lässt sich durch herumexperimentieren aber sicher minimieren. Sehr trinkbar. Ist halt sein Charakter. > Tre Forze <",
        "Geschmack": "",
        "Wiederkaufen": "Vielleicht"
    },
    {
        "Full Post": "AW: Ich trinke gerade diesen Espresso.... Name der Bohne: Blasercafé Brasil Corazon Packungsgröße: 250 Gramm Gemahlen und Bezogen mit: K3 / Perfetta Gekauft: Dezember MHD: 4.11.2009 Eigenschaften: Feine dünne Crema. Äußerst aromatisch und das ohne Bitter oder Sauer zu sein. Superlecker. Ein Espresso der von der Brühtemperatur her unempfindlich scheint. Also unkompliziert. Mahlgrad sehr grob. Wieder kaufen: Warum nicht",
        "Name": "Blasercafé Brasil Corazon",
        "Packungsgröße": "250 Gramm",
        "Maschine": "K3 / Perfetta Gekauft: Dezember",
        "Gekauft am": "",
        "MHD": "4.11.2009",
        "Eigenschaften": "Feine dünne Crema. Äußerst aromatisch und das ohne Bitter oder Sauer zu sein. Superlecker. Ein Espresso der von der Brühtemperatur her unempfindlich scheint. Also unkompliziert. Mahlgrad sehr grob.",
        "Geschmack": "",
        "Wiederkaufen": "Warum nicht"
    },
    {
        "Full Post": "AW: Ich trinke gerade diesen Espresso.... Name der Bohne: Blaser Lilla e Rose Packungsgröße: 250 Gramm Gemahlen und Bezogen mit: Gaggia Roma/Gaggia CC Gekauft: 15.12.2008 MHD: 15.09.2009 Eigenschaften: Mitteldunkle Röstung, etwas heller als der Italia aus dem gleichen Haus. Macht sich nicht schlecht als Espresso! Die Geschmacksbeschreibung der Kaffeezentrale trifft soweit zu. Crema nicht ganz so üppig wie beim Mauro Espresso Bar, aber doch anständige Schicht. Ob sich die Bohnen für etwas längeren Espresso oder kurzen Ristretto besser eignen, werde ich in den nächsten Tagen herausfinden. Kleiner Nachtrag noch zum Mauro Espresso Bar, den ich anfangs als eher marzipanig-dünn empfunden habe: Man muss ihn stark genug machen, dann kann sehr intensiver Ristretto daraus werden! Bezugszeit bei meiner nicht brühdruckreduzierten Gaggia: 23 Sekunden. Zwischen 24 und 25 Sekunden liegt die Bitter-Grenze. Wieder kaufen: Ich denke schon!",
        "Name": "Blaser Lilla e Rose",
        "Packungsgröße": "250 Gramm",
        "Maschine": "Gaggia Roma/Gaggia CC Gekauft: 15.12.2008",
        "Gekauft am": "",
        "MHD": "15.09.2009",
        "Eigenschaften": "Mitteldunkle Röstung, etwas heller als der Italia aus dem gleichen Haus. Macht sich nicht schlecht als Espresso! Die sbeschreibung der Kaffeezentrale trifft soweit zu. Crema nicht ganz so üppig wie beim Mauro Espresso Bar, aber doch anständige Schicht. Ob sich die Bohnen für etwas längeren Espresso oder kurzen Ristretto besser eignen, werde ich in den nächsten Tagen herausfinden. Kleiner Nachtrag noch zum Mauro Espresso Bar, den ich anfangs als eher marzipanig-dünn empfunden habe: Man muss ihn stark genug machen, dann kann sehr intensiver Ristretto daraus werden! Bezugszeit bei meiner nicht brühdruckreduzierten Gaggia: 23 Sekunden. Zwischen 24 und 25 Sekunden liegt die Bitter-Grenze.",
        "Geschmack": "",
        "Wiederkaufen": "Ich denke schon!"
    },
    {
        "Full Post": "AW: Ich trinke gerade diesen Espresso.... Name der Bohne: Blaser Café Ethiopia Sidamo Packungsgröße: 250 Gramm Gemahlen und Bezogen mit: K3 / Perfetta Gekauft: Dezember MHD: 29.07.2009 Eigenschaften: Wie der Corazon: Feine dünne Crema. Ebenfalls äußerst aromatisch ohne Bitter oder Sauer zu sein. Ebenso ein Genuss. Süsser Geschmack. Was man schon nach dem mahlen erduftet. Tritt stark und schnell auf und wirkt angenehm nach. Bisserl Säure die aber sehr fein und angenehm ist. Wieder kaufen: Obschon sehr gut: eher nicht.",
        "Name": "Blaser Café Ethiopia Sidamo",
        "Packungsgröße": "250 Gramm",
        "Maschine": "K3 / Perfetta Gekauft: Dezember",
        "Gekauft am": "",
        "MHD": "29.07.2009",
        "Eigenschaften": "Wie der Corazon: Feine dünne Crema. Ebenfalls äußerst aromatisch ohne Bitter oder Sauer zu sein. Ebenso ein Genuss. Süsser . Was man schon nach dem mahlen erduftet. Tritt stark und schnell auf und wirkt angenehm nach. Bisserl Säure die aber sehr fein und angenehm ist.",
        "Geschmack": "",
        "Wiederkaufen": "Obschon sehr gut: eher nicht."
    },
    {
        "Full Post": "AW: Ich trinke gerade diesen Espresso.... Name der Bohne: Fausto Monaco Packungsgröße: 2 x 250 Gramm Gemahlen und Bezogen mit: Lux/Oscar Gekauft: Dezember MHD: 12/09 Eigenschaften: Der Klassiker unter den Faustos. Habe ich lange nicht mehr gekauft - und entweder habe ich als Barista Fortschritte gemacht oder Meister Fausto \"Il Giasinga\" hat nochmal eine Schippe draufgelegt: Sehr \"schöner\" Kaffee, fruchtig, spritzig, modern. Erinnert mich an norditalienische Barkaffees. Geht ohne Zucker, geht mit Zucker, pur und als Cappu! Complimenti Maestro!!! Wieder kaufen: Naturalmente, wase fragste Du so dumme!! Gruss Plempel",
        "Name": "Fausto Monaco",
        "Packungsgröße": "2 x 250 Gramm",
        "Maschine": "Lux/Oscar Gekauft: Dezember",
        "Gekauft am": "",
        "MHD": "12/09",
        "Eigenschaften": "Der Klassiker unter den Faustos. Habe ich lange nicht mehr gekauft - und entweder habe ich als Barista Fortschritte gemacht oder Meister Fausto \"Il Giasinga\" hat nochmal eine Schippe draufgelegt: Sehr \"schöner\" Kaffee, fruchtig, spritzig, modern. Erinnert mich an norditalienische Barkaffees. Geht ohne Zucker, geht mit Zucker, pur und als Cappu! Complimenti Maestro!!!",
        "Geschmack": "",
        "Wiederkaufen": "Naturalmente, wase fragste Du so dumme!! Gruss Plempel"
    },
    {
        "Full Post": "AW: Ich trinke gerade diesen Espresso.... Name der Bohne: MANTACCO Packungsgröße: 1000 Gramm Gemahlen und Bezogen mit: Mazzer Super Jolly / Astoria Lady Gekauft am: Angang September MHD: 11/09 Eigenschaften: feine Note von dunkler Schokolade Die Mischung besteht aus ca. 95% Arabica und 5% Robusta. Die Mischung ist frisch geröstet Wieder kaufen: wahrscheinlich",
        "Name": "MANTACCO",
        "Packungsgröße": "1000 Gramm",
        "Maschine": "Mazzer Super Jolly / Astoria Lady",
        "Gekauft am": "Angang September",
        "MHD": "11/09",
        "Eigenschaften": "feine Note von dunkler Schokolade Die Mischung besteht aus ca. 95% Arabica und 5% Robusta. Die Mischung ist frisch geröstet",
        "Geschmack": "",
        "Wiederkaufen": "wahrscheinlich"
    },
    {
        "Full Post": "AW: Ich trinke gerade diesen Espresso.... Zitat von matt: ↑ Name der Bohne: Blaser Café Ethiopia Sidamo Packungsgröße: 250 Gramm Gemahlen und Bezogen mit: K3 / Perfetta Gekauft: Dezember MHD: 29.07.2009 Eigenschaften: Wie der Corazon: Feine dünne Crema. Ebenfalls äußerst aromatisch ohne Bitter oder Sauer zu sein. Ebenso ein Genuss. Süsser Geschmack. Was man schon nach dem mahlen erduftet. Tritt stark und schnell auf und wirkt angenehm nach. Bisserl Säure die aber sehr fein und angenehm ist. Wieder kaufen: Obschon sehr gut: eher nicht.Klicke in dieses Feld, um es in vollständiger Größe anzuzeigen. Kleiner Nachtrag: Obiges gilt für LM-Sieb. Ganz anders im Original BFC Einersieb. Dort mit 9,5 bis 10 Gramm riecht und schmeckt man die Aprikosen und Pfirsichnoten. Im LM mit 7 bis 7,5 Gramm schmeckt er eher nach Rosinen. Im BFC-Sieb eine absolute Wucht. Ein Kaffee mit eben deutlichen Noten und Charakter. lg matt",
        "Name": "Blaser Café Ethiopia Sidamo",
        "Packungsgröße": "250 Gramm",
        "Maschine": "K3 / Perfetta Gekauft: Dezember",
        "Gekauft am": "",
        "MHD": "29.07.2009",
        "Eigenschaften": "Wie der Corazon: Feine dünne Crema. Ebenfalls äußerst aromatisch ohne Bitter oder Sauer zu sein. Ebenso ein Genuss. Süsser . Was man schon nach dem mahlen erduftet. Tritt stark und schnell auf und wirkt angenehm nach. Bisserl Säure die aber sehr fein und angenehm ist.",
        "Geschmack": "",
        "Wiederkaufen": "Obschon sehr gut: eher nicht.Klicke in dieses Feld, um es in vollständiger Größe anzuzeigen. Kleiner Nachtrag: Obiges gilt für LM-Sieb. Ganz anders im Original BFC Einersieb. Dort mit 9,5 bis 10 Gramm riecht und schmeckt man die Aprikosen und Pfirsichnoten. Im LM mit 7 bis 7,5 Gramm schmeckt er eher nach Rosinen. Im BFC-Sieb eine absolute Wucht. Ein Kaffee mit eben deutlichen Noten und Charakter. lg matt"
    },
    {
        "Full Post": "Name der Bohne: Blaser Café Ethiopia Sidamo Packungsgröße: 250 Gramm Gemahlen und Bezogen mit: K3 / Perfetta Gekauft: Dezember MHD: 29.07.2009 Eigenschaften: Wie der Corazon: Feine dünne Crema. Ebenfalls äußerst aromatisch ohne Bitter oder Sauer zu sein. Ebenso ein Genuss. Süsser Geschmack. Was man schon nach dem mahlen erduftet. Tritt stark und schnell auf und wirkt angenehm nach. Bisserl Säure die aber sehr fein und angenehm ist. Wieder kaufen: Obschon sehr gut: eher nicht.Klicke in dieses Feld, um es in vollständiger Größe anzuzeigen.",
        "Name": "Blaser Café Ethiopia Sidamo",
        "Packungsgröße": "250 Gramm",
        "Maschine": "K3 / Perfetta Gekauft: Dezember",
        "Gekauft am": "",
        "MHD": "29.07.2009",
        "Eigenschaften": "Wie der Corazon: Feine dünne Crema. Ebenfalls äußerst aromatisch ohne Bitter oder Sauer zu sein. Ebenso ein Genuss. Süsser . Was man schon nach dem mahlen erduftet. Tritt stark und schnell auf und wirkt angenehm nach. Bisserl Säure die aber sehr fein und angenehm ist.",
        "Geschmack": "",
        "Wiederkaufen": "Obschon sehr gut: eher nicht.Klicke in dieses Feld, um es in vollständiger Größe anzuzeigen."
    },
    {
        "Full Post": "AW: Ich trinke gerade diesen Espresso.... Name der Bohne: Caffé Crema aus dem Probierpaket von Caffé Fausto Packungsgröße: 250 Gramm Gemahlen und Bezogen mit: Iberital Challenge / Gaggia Baby Class Gekauft am: Lieferung erfolgte am 19. Dezember MHD: 12/09 (geröstet am 17.12.) Eigenschaften: Habe die Packung heute geöffnet. Nach den ersten Testbezügen recht zwiespältiger Eindruck. Dünne, helle Crema. Als Anfänger fällt es mir schwer den Geschmack richtig zu beschreiben, aber ich würde ihn als leicht fruchtig und leicht säuerlich beschreiben. Nicht so markant wie der Malabar, den ich vorher hatte. Der Crema hat auch nicht so einen vollen Körper. Weitere Bezüge werden zeigen, ob es so bleibt. Wieder kaufen: Momentan wohl eher nicht. Kurzer Nachtrag: Auch bei weiteren Versuchen hat mir der Caffé Crema als Espresso überhaupt nicht zugesagt; irgendwie erinnert er mich an das Zeug, das als \"Espresso\" aus VA'a rauskommt. Als Langer Kaffee (Lungo?) ist er jedoch durchaus brauchbar. Habe etwa 8gr in ein 2er-Sieb gefüllt, fest getampt und in knapp 30 sek. eine Lungo-Tasse befüllt. Der Mahlgrad ist gröber als bei einem Espresso. Ich trinke \"normalen\" Kaffee (also auch Lungo) immer ohne Zucker; auch so schmeckt er wirklich nicht schlecht und ist auch nicht bitter. So sind die restlichen Bohnen doch nicht für die Tonne! :-D",
        "Name": "Caffé Crema aus dem Probierpaket von Caffé Fausto",
        "Packungsgröße": "250 Gramm",
        "Maschine": "Iberital Challenge / Gaggia Baby Class",
        "Gekauft am": "Lieferung erfolgte am 19. Dezember",
        "MHD": "12/09 (geröstet am 17.12.)",
        "Eigenschaften": "Habe die Packung heute geöffnet. Nach den ersten Testbezügen recht zwiespältiger Eindruck. Dünne, helle Crema. Als Anfänger fällt es mir schwer den  richtig zu beschreiben, aber ich würde ihn als leicht fruchtig und leicht säuerlich beschreiben. Nicht so markant wie der Malabar, den ich vorher hatte. Der Crema hat auch nicht so einen vollen Körper. Weitere Bezüge werden zeigen, ob es so bleibt.",
        "Geschmack": "",
        "Wiederkaufen": "Momentan wohl eher nicht. Kurzer Nachtrag: Auch bei weiteren Versuchen hat mir der Caffé Crema als Espresso überhaupt nicht zugesagt; irgendwie erinnert er mich an das Zeug, das als \"Espresso\" aus VA'a rauskommt. Als Langer Kaffee (Lungo?) ist er jedoch durchaus brauchbar. Habe etwa 8gr in ein 2er-Sieb gefüllt, fest getampt und in knapp 30 sek. eine Lungo-Tasse befüllt. Der Mahlgrad ist gröber als bei einem Espresso. Ich trinke \"normalen\" Kaffee (also auch Lungo) immer ohne Zucker; auch so schmeckt er wirklich nicht schlecht und ist auch nicht bitter. So sind die restlichen Bohnen doch nicht für die Tonne! :-D"
    },
    {
        "Full Post": "AW: Ich trinke gerade diesen Espresso.... Hallo, Name der Bohne: [FONT=Verdana, Arial, Helvetica, sans-serif]world´s end finest coffee Blend LATINO[/FONT] Packungsgröße: 250 Gramm Gemahlen und Bezogen mit: Ascaso I-Steel/Bezzera BZ07 Gekauft am: Ende Dezember MHD: 12/09 Eigenschaften: Bohnen nicht zu dunkel geröstet. Am Anfang fand ich ihn sehr flach, wollte schon die Bohnen wechseln, doch dann feiner gemahlen und nur leicht getampert, vollmundig, leicht schokoladig und etwas fruchtig. Leichte Säure, mein erster Espresso der mir mit Zucker zu süss war. Crema stabil aber nicht allzuviel. Wieder kaufen: Erstmal Röster in der Nähe probieren, denke aber schon. Grüsse Ingo",
        "Name": "[FONT=Verdana, Arial, Helvetica, sans-serif]world´s end finest coffee Blend LATINO[/FONT]",
        "Packungsgröße": "250 Gramm",
        "Maschine": "Ascaso I-Steel/Bezzera BZ07",
        "Gekauft am": "Ende Dezember",
        "MHD": "12/09",
        "Eigenschaften": "Bohnen nicht zu dunkel geröstet. Am Anfang fand ich ihn sehr flach, wollte schon die Bohnen wechseln, doch dann feiner gemahlen und nur leicht getampert, vollmundig, leicht schokoladig und etwas fruchtig. Leichte Säure, mein erster Espresso der mir mit Zucker zu süss war. Crema stabil aber nicht allzuviel.",
        "Geschmack": "",
        "Wiederkaufen": "Erstmal Röster in der Nähe probieren, denke aber schon. Grüsse Ingo"
    },
    {
        "Full Post": "AW: Ich trinke gerade diesen Espresso.... Name der Bohne: [FONT=Verdana, Arial, Helvetica, sans-serif]Perlanera[/FONT] Packungsgröße: 1000 Gramm Gemahlen und Bezogen mit: Mazzer mini E/Cimbali Junior Gekauft am: 26. 12.2008 MHD: 08/10 Eigenschaften: Bohnen nicht zu dunkel geröstet. Crema stabil und viel. Wieder kaufen: vielleicht",
        "Name": "[FONT=Verdana, Arial, Helvetica, sans-serif]Perlanera[/FONT]",
        "Packungsgröße": "1000 Gramm",
        "Maschine": "Mazzer mini E/Cimbali Junior",
        "Gekauft am": "26. 12.2008",
        "MHD": "08/10",
        "Eigenschaften": "Bohnen nicht zu dunkel geröstet. Crema stabil und viel.",
        "Geschmack": "",
        "Wiederkaufen": "vielleicht"
    },
    {
        "Full Post": "AW: Ich trinke gerade diesen Espresso.... Name der Bohne: Peru von Caffé Fausto Packungsgröße: 250 Gramm Gemahlen und Bezogen mit: Iberital Challenge / Gaggia Baby Class Gekauft am: Lieferung erfolgte am 19. Dezember MHD: 12/09 (geröstet am 17.12.) Eigenschaften: Die Packung habe ich heute geöffnet und nach einer Stunde die ersten zwei Bezüge gemacht (Single-Shots). Schon der zweite Bezug sah optisch recht gut aus; schöne Mäuseschwänzchen, mittelbraune Crema. Geschmacklich kann ich dem zustimmen, was bisher über den Peru geschrieben wurde: Nussiges, fast schon erdiges Aroma, etwas dünn (oder mild, wie es andere nennen). Werde morgen meine ersten Eindrücke ergänzen, wenn die Bohnen Zeit hatten, im Bohnenbehälter zu atmen. Erfahrungsgemäß ändert sich dann noch ein wenig. Außerdem muss ich noch ein wenig am Mahlgrad schrauben. Dem ersten Eindruck nach zu urteilen kann er aber dem Malabar (meinem bisherigen Favoriten) nicht das Wasser reichen. Wieder kaufen: Dazu kann ich noch nichts sagen. Nachtrag: Nach einer Nacht im Bohnenbehälter habe ich den Mahlgrad weiter verfeinert. Geschmacklich immer noch recht dünn (ebenso wie die Crema). Also etwas mehr Pulver ins Sieb; allerdings klebte nun der Puck am Duschsieb. Aber so langsam nähere ich mich dem Optimalzustand und der Peru entwickelt einen Geschmack, dem man doch etwas abgewinnen kann. Er ist in der tat schwieriger als der Malabar und hat eine ganz andere Note.",
        "Name": "Peru von Caffé Fausto",
        "Packungsgröße": "250 Gramm",
        "Maschine": "Iberital Challenge / Gaggia Baby Class",
        "Gekauft am": "Lieferung erfolgte am 19. Dezember",
        "MHD": "12/09 (geröstet am 17.12.)",
        "Eigenschaften": "Die Packung habe ich heute geöffnet und nach einer Stunde die ersten zwei Bezüge gemacht (Single-Shots). Schon der zweite Bezug sah optisch recht gut aus; schöne Mäuseschwänzchen, mittelbraune Crema. lich kann ich dem zustimmen, was bisher über den Peru geschrieben wurde: Nussiges, fast schon erdiges Aroma, etwas dünn (oder mild, wie es andere nennen). Werde morgen meine ersten Eindrücke ergänzen, wenn die Bohnen Zeit hatten, im Bohnenbehälter zu atmen. Erfahrungsgemäß ändert sich dann noch ein wenig. Außerdem muss ich noch ein wenig am Mahlgrad schrauben. Dem ersten Eindruck nach zu urteilen kann er aber dem Malabar (meinem bisherigen Favoriten) nicht das Wasser reichen.",
        "Geschmack": "",
        "Wiederkaufen": "Dazu kann ich noch nichts sagen. Nachtrag: Nach einer Nacht im Bohnenbehälter habe ich den Mahlgrad weiter verfeinert. lich immer noch recht dünn (ebenso wie die Crema). Also etwas mehr Pulver ins Sieb; allerdings klebte nun der Puck am Duschsieb. Aber so langsam nähere ich mich dem Optimalzustand und der Peru entwickelt einen , dem man doch etwas abgewinnen kann. Er ist in der tat schwieriger als der Malabar und hat eine ganz andere Note."
    },
    {
        "Full Post": "AW: Ich trinke gerade diesen Espresso.... Name der Bohne: Quarta Avio Packungsgröße: 500 Gramm Gemahlen und Bezogen mit: Gaggia Roma/Gaggia Classic Gekauft am: 30. Dezember im ItalFruit, Bern MHD: 04/09 Eigenschaften: Neben Bitternoten und fauler Banane nicht viel Erfreuliches. Wahrscheinlich zu alt. Werde noch etwas experimentieren. Wieder kaufen: Wozu sollte ich?",
        "Name": "Quarta Avio",
        "Packungsgröße": "500 Gramm",
        "Maschine": "Gaggia Roma/Gaggia Classic",
        "Gekauft am": "30. Dezember im ItalFruit, Bern",
        "MHD": "04/09",
        "Eigenschaften": "Neben Bitternoten und fauler Banane nicht viel Erfreuliches. Wahrscheinlich zu alt. Werde noch etwas experimentieren.",
        "Geschmack": "",
        "Wiederkaufen": "Wozu sollte ich?"
    },
    {
        "Full Post": "AW: Ich trinke gerade diesen Espresso.... Name der Bohne: Mauro Espresso Bar Packungsgröße: 1000 Gramm Gemahlen und Bezogen mit: Gaggia Roma/Gaggia Classic Gekauft am: 31. Dezember (per Post eingetroffen von Kaffeezentrale) MHD: 10/10 Eigenschaften: Wieder mal... Der Quarta Avio war nicht lange in der Mühle, damit war wirklich nichts anzufangen. Den Mauro habe ich schon mal beschrieben, man muss ihn stark genug machen, dann kommen neben den süsslichen auch \"dunklere\", nicht bittere Aromen zum Vorschein. Sehr gut geeignet für Ristretto. Ich habe heute mit Hilfe von drei Doppios einen Tiramisu zum Geburtstag meiner Frau fabriziert. Wieder kaufen: Aber sicher!",
        "Name": "Mauro Espresso Bar",
        "Packungsgröße": "1000 Gramm",
        "Maschine": "Gaggia Roma/Gaggia Classic",
        "Gekauft am": "31. Dezember (per Post eingetroffen von Kaffeezentrale)",
        "MHD": "10/10",
        "Eigenschaften": "Wieder mal... Der Quarta Avio war nicht lange in der Mühle, damit war wirklich nichts anzufangen. Den Mauro habe ich schon mal beschrieben, man muss ihn stark genug machen, dann kommen neben den süsslichen auch \"dunklere\", nicht bittere Aromen zum Vorschein. Sehr gut geeignet für Ristretto. Ich habe heute mit Hilfe von drei Doppios einen Tiramisu zum Geburtstag meiner Frau fabriziert.",
        "Geschmack": "",
        "Wiederkaufen": "Aber sicher!"
    },
    {
        "Full Post": "AW: Ich trinke gerade diesen Espresso.... Name der Bohne: Picada Livorno Packungsgröße: 250 Gramm (aus dem Probierpaket im verschweißten Beutel ohne Ventil) Gemahlen und Bezogen mit: Anfim/Domobar Gekauft: Ende Dezember MHD: 02/01/10 Eigenschaften: Zunächst mal zur Eigenschaft des Service. Hatte meinen Warenkorb in der elektronischen Filiale von Picada nicht abgeschickt. Und dann am 30.12. telefonisch nachgehakt und eine noch immer erstaunlich unerschütterliche Dame am Telefon - Chefin selbst. Trotz meines Fehlers bat sie um Verständnis - völlig überflüssig natürlich. Ich sagte, dass ich noch Bohnen für gut eine bis zwei Wochen hätte - und heute klingelt der Postmann. Röstdatum 2.1.09. Freunde, geht's frischer im neuen Jahr? Erster Versuch: Eigentlich schon super. Jedenfalls wüsste ich spontan nicht, was besser sein könnte. Da es nur eine Tasse war, liefere ich mal die Eigenschaften nach per Änderung. Anbei Bilder, die beweisen, wie frisch die Bohnen bei mir ankamen. So, ich reiche es mal nach mit den Eindrücken. Mit der rechten Menge Zucker, mal ausnahmsweise etwas mehr, ist das eine fette Praline. Schön schokoladig. Wie immer, wenn es etwas harmonisch ist, mag ich es auch. Auch diesen Livorno. Meine Frau fand ihn \"eigenschaftsloser\" als den Gastronomen-Lavazza aus der blauen Packung, dessen Reste ich gerade noch aufgebraucht habe. Der hatte mehr fruchtige Noten, die dem Livorno vollständig abgehen. Was mir recht ist. Also: dezente Schokobohne, die mir gut gefällt. Die sehr feine Mahlung und Beschränkung auf 14 Gramm (mache immer doppelte) sind ja auch nicht schlecht. Nach leichtem Tampern ist der Siebträger fast leer. Der Lavazza davor war gröber und mit 15 Gramm weit drüber und erst dann einigermaßen kontrollierbar. Der Livorno mit 15 Gramm und der jetzigen Mahlung kommt allerdings kaum noch raus. Was so ein Gramm ausmacht, ist schon erstaunlich. Das ist ein stückweit ärgerlich, weil ich das abwiegen eigentlich nicht so mag. Lieber per Auge mahlen. Das geht hier scheinbar nicht. Wieder kaufen? Erstmal die anderen Picadas probieren!!!! ;-)",
        "Name": "Picada Livorno",
        "Packungsgröße": "250 Gramm (aus dem Probierpaket im verschweißten Beutel ohne Ventil)",
        "Maschine": "Anfim/Domobar Gekauft: Ende Dezember",
        "Gekauft am": "",
        "MHD": "02/01/10",
        "Eigenschaften": "",
        "Geschmack": "",
        "Wiederkaufen": ""
    },
    {
        "Full Post": "AW: Ich trinke gerade diesen Espresso.... Name der Bohne: Monaco von Caffé Fausto Packungsgröße: 250 Gramm Gemahlen und Bezogen mit: Iberital Challenge / Gaggia Baby Class Gekauft am: Lieferung erfolgte am 19. Dezember MHD: 12/09 (geröstet am 17.12.) Eigenschaften: Erinnert mich etwas an den Peru, jedoch kräftiger im Geschmack. Er ist auch leichter handhabbar. Die Crema hat eine angenehme Dicke, der Geschmack ist sehr angenehm. Im großen und ganzen kann ich mich der Meinung von \"dergitarrist\" eine Seite vorher anschließen. Meinen bisherigen Liebling Malabar kann er trotzdem nicht von Platz eins verdrängen. Wieder kaufen: Sicherlich.",
        "Name": "Monaco von Caffé Fausto",
        "Packungsgröße": "250 Gramm",
        "Maschine": "Iberital Challenge / Gaggia Baby Class",
        "Gekauft am": "Lieferung erfolgte am 19. Dezember",
        "MHD": "12/09 (geröstet am 17.12.)",
        "Eigenschaften": "Erinnert mich etwas an den Peru, jedoch kräftiger im . Er ist auch leichter handhabbar. Die Crema hat eine angenehme Dicke, der  ist sehr angenehm. Im großen und ganzen kann ich mich der Meinung von \"dergitarrist\" eine Seite vorher anschließen. Meinen bisherigen Liebling Malabar kann er trotzdem nicht von Platz eins verdrängen.",
        "Geschmack": "",
        "Wiederkaufen": "Sicherlich."
    },
    {
        "Full Post": "AW: Ich trinke gerade diesen Espresso.... Name der Bohne: Indien Balmany Organic (100% Robusta), gekauft bei Da Capo in Lemgo Packungsgröße: 250 Gramm für 7,50€ Gemahlen und Bezogen mit: Handmühle und Aldi-espressofant terrible :roll: (ohne Cremadüse!!!) Gekauft am: geröstet morgens am Kaufdatum 08.01.09 MHD: Eigenschaften: Toller Espresso aus 100% Robusta, recht mild aber würzig, schokoladig. Klasse Crema. Gefällt mir besser als die meisten Arabica Espressos. Sehr unkomplizierter Kaffee. Wieder kaufen: Ja! :lol:",
        "Name": "Indien Balmany Organic (100% Robusta), gekauft bei Da Capo in Lemgo",
        "Packungsgröße": "250 Gramm für 7,50€",
        "Maschine": "Handmühle und Aldi-espressofant terrible :roll: (ohne Cremadüse!!!)",
        "Gekauft am": "geröstet morgens am Kaufdatum 08.01.09",
        "MHD": ": Toller Espresso aus 100% Robusta, recht mild aber würzig, schokoladig. Klasse Crema. Gefällt mir besser als die meisten Arabica Espressos. Sehr unkomplizierter Kaffee.",
        "Eigenschaften": "Toller Espresso aus 100% Robusta, recht mild aber würzig, schokoladig. Klasse Crema. Gefällt mir besser als die meisten Arabica Espressos. Sehr unkomplizierter Kaffee.",
        "Geschmack": "",
        "Wiederkaufen": "Ja! :lol:"
    },
    {
        "Full Post": "AW: Ich trinke gerade diesen Espresso.... Name der Bohne: Caffee Compagnie - Papua Neuguinea Red Mountain (single origin) Packungsgröße: 250 Gramm für 5,50€ Gemahlen und Bezogen mit: Zassenhaus 156 / Silvia (LM1 im bodenlosen ST) Gekauft am: kurz vor Weihnachten MHD: 11/2009 (12M) Eigenschaften: Feine Säure ist eine der wenigen Eigenschaften, die mir noch einfallen. Ich fand ihn sonst sehr ausgewogen, leicht würzig, durchaus kräftig. Macht sich wohl im Cappu auch recht gut. Wieder kaufen: Da ich ihn lokal bekommen kann wohl eher schon, aber erst mal durchtesten",
        "Name": "Caffee Compagnie - Papua Neuguinea Red Mountain (single origin)",
        "Packungsgröße": "250 Gramm für 5,50€",
        "Maschine": "Zassenhaus 156 / Silvia (LM1 im bodenlosen ST)",
        "Gekauft am": "kurz vor Weihnachten",
        "MHD": "11/2009 (12M)",
        "Eigenschaften": "Feine Säure ist eine der wenigen , die mir noch einfallen. Ich fand ihn sonst sehr ausgewogen, leicht würzig, durchaus kräftig. Macht sich wohl im Cappu auch recht gut.",
        "Geschmack": "",
        "Wiederkaufen": "Da ich ihn lokal bekommen kann wohl eher schon, aber erst mal durchtesten"
    },
    {
        "Full Post": "AW: Ich trinke gerade diesen Espresso.... Name der Bohne: Caffe del Moro Kaffee Espresso - Grangusto Packungsgröße: 1000 Gramm Gemahlen und Bezogen mit: s. Signatur Gekauft am: 29. August 2008 MHD: Juli 2009 MHD in Monaten: laut espressosorten.de 24 Monate laut aromatico.de 18 Monate Eigenschaften: Einstellung des Mahlgrads auch nach ca. 500 g im Dauerversuch nahezu unmöglich. Crema üppig. Geschmack: Bitterschokolade, untrinkbar. Undifferenzierter Robustabomber. Wieder kaufen: Never again, auch nicht geschenkt, nicht verbrauchter Rest wurde entsorgt! Jetzt: Danesi Doppio, alles wieder im Lot!",
        "Name": "Caffe del Moro Kaffee Espresso - Grangusto",
        "Packungsgröße": "1000 Gramm",
        "Maschine": "s. Signatur",
        "Gekauft am": "29. August 2008",
        "MHD": "Juli 2009  in Monaten: laut espressosorten.de 24 Monate laut aromatico.de 18 Monate",
        "Eigenschaften": "Einstellung des Mahlgrads auch nach ca. 500 g im Dauerversuch nahezu unmöglich. Crema üppig.",
        "Geschmack": "Bitterschokolade, untrinkbar. Undifferenzierter Robustabomber.",
        "Wiederkaufen": "Never again, auch nicht geschenkt, nicht verbrauchter Rest wurde entsorgt! Jetzt: Danesi Doppio, alles wieder im Lot!"
    },
    {
        "Full Post": "AW: Ich trinke gerade diesen Espresso.... Name der Bohne: Giasing von Caffé Fausto Packungsgröße: 250 Gramm Gemahlen und Bezogen mit: Iberital Challenge / Gaggia Baby Class Gekauft am: Lieferung erfolgte am 19. Dezember MHD: 12/09 (geröstet am 17.12.) Eigenschaften: Vorab: ein Super Espresso! Der Giasing trifft genau meinen Geschmack; er hat einen vollen Körper, tolle Crema und verzeiht wie der Malabar auch Fehler bei der Zubereitung. Um Herrn plempel zu zitieren: Unverkopft, unprätentiös, unkompliziert, einfach \"bohnig\". Kommt meinem Geschmack und meiner \"Zubereitungsweise\" sehr entgegen. Der Giasing hat den Faustos noch gefehlt. Reschpekt, Dottore Fausto!Klicke in dieses Feld, um es in vollständiger Größe anzuzeigen. Wieder kaufen: Schon geschehen! :-D",
        "Name": "Giasing von Caffé Fausto",
        "Packungsgröße": "250 Gramm",
        "Maschine": "Iberital Challenge / Gaggia Baby Class",
        "Gekauft am": "Lieferung erfolgte am 19. Dezember",
        "MHD": "12/09 (geröstet am 17.12.)",
        "Eigenschaften": "Vorab: ein Super Espresso! Der Giasing trifft genau meinen ; er hat einen vollen Körper, tolle Crema und verzeiht wie der Malabar auch Fehler bei der Zubereitung. Um Herrn plempel zu zitieren: Unverkopft, unprätentiös, unkompliziert, einfach \"bohnig\". Kommt meinem  und meiner \"Zubereitungsweise\" sehr entgegen. Der Giasing hat den Faustos noch gefehlt. Reschpekt, Dottore Fausto!Klicke in dieses Feld, um es in vollständiger Größe anzuzeigen.",
        "Geschmack": "",
        "Wiederkaufen": "Schon geschehen! :-D"
    },
    {
        "Full Post": "AW: Ich trinke gerade diesen Espresso.... Name der Bohne: Blaser, Lilla e Rose Packungsgröße: 250 Gramm, Aromaventil Gemahlen und Bezogen mit: s. Signatur Gekauft am: 16.12.2008 MHD: 13.11.2009 MHD in Monaten: laut aromatico.de 12 Monate Eigenschaften: Mahlgrad im Vergleich zum Danesi Doppio etwas feiner eingestellt, sehr gleichmäßiges Mahlgut, keine Klümppchenbildung, läuft ohne Probleme, schöne, stabile Crema, feiner Duft. Geschmack: Vielschichtige, differenzierte Röstaromen, leicht fruchtige, säurebetonte Note, voller Geschmack, anhaltender Abgang. Behält seinen vollen kräftigen Geschmack auch im Cappuccino. Wieder kaufen: Jederzeit. :lol:",
        "Name": "Blaser, Lilla e Rose",
        "Packungsgröße": "250 Gramm, Aromaventil",
        "Maschine": "s. Signatur",
        "Gekauft am": "16.12.2008",
        "MHD": "13.11.2009  in Monaten: laut aromatico.de 12 Monate",
        "Eigenschaften": "Mahlgrad im Vergleich zum Danesi Doppio etwas feiner eingestellt, sehr gleichmäßiges Mahlgut, keine Klümppchenbildung, läuft ohne Probleme, schöne, stabile Crema, feiner Duft.",
        "Geschmack": "Vielschichtige, differenzierte Röstaromen, leicht fruchtige, säurebetonte Note, voller , anhaltender Abgang. Behält seinen vollen kräftigen  auch im Cappuccino.",
        "Wiederkaufen": "Jederzeit. :lol:"
    },
    {
        "Full Post": "AW: Ich trinke gerade diesen Espresso.... Name der Bohne: Mocambo Gran Bar (Goldene Packung) NICHT MOKAMBO!!! Packungsgröße: 1000 Gramm Packung => Aromaventil Gemahlen und Bezogen mit: Bezzera/Domobar (die cimbali zickt noch) Gekauft am: 24.01.09 MHD: 12/10 Eigenschaften: Auf eine seltsame Art kräftig und mild zugleich. Geht eigentlich nicht. Kommt mir aber dennoch so vor. Ich bin mental gerade mehr am Schrauben und \"nutze\" den Kaffee derzeit eigentlich mehr, als ihm hinterherzuspüren. Den Mocambo aus Radevormwald trifft keine Schuld. Mein örtlicher italienischer Supermarkt auf dem Hof eines Fabrikgeländes hat ihn in großer Menge - jedenfalls mehr als alle anderen Sorten. Könnte an der geographischen Nähe zu Radevormwald liegen. Bei näheren Erkenntnissen schiebe ich die hinterher. Hier neue Erkenntnis (die keine ist): Schmeckt heute morgen als Cappu und Espresso so, wie oben beschrieben. Nett mild. Wieder kaufen? Lieber den silbernen. (jetzt bekomme ich aber erstmal Post aus München. Bin dem Forumsmarketing hier erlegen... ;-))",
        "Name": "Mocambo Gran Bar (Goldene Packung) NICHT MOKAMBO!!!",
        "Packungsgröße": "1000 Gramm Packung => Aromaventil",
        "Maschine": "Bezzera/Domobar (die cimbali zickt noch)",
        "Gekauft am": "24.01.09",
        "MHD": "12/10",
        "Eigenschaften": "",
        "Geschmack": "",
        "Wiederkaufen": ""
    },
    {
        "Full Post": "AW: Ich trinke gerade diesen Espresso.... Name der Bohne: Ferrari Napoli Packungsgröße: 250 Gramm Gemahlen und Bezogen mit: Gaggia Roma/Gaggia Classic Gekauft am: 27. Januar MHD: 31.03.09 Eigenschaften: Geliefert im Papiersack, 3 Monate haltbar. Bei den Ventilbeuteln habe ich jeweils den Eindruck, dass der Kaffee nach 1 oder 2 Tagen in der Mühle noch etwas aufblüht. Der Ferrari hatte nun also schon fast einen Monat Zeit, um in der Papiertüte \"aufzublühen\". Vielleicht ist das etwas lang, aber ich habe keine Vergleichsmöglichkeit mit frisch Geröstetem. Nun zum Kaffee selbst: Fast schwarz geröstete Arabica-Bohnen mit dicker Oelschicht. Klebrig. Ich brauchte einige Versuche, bis die Bohnen überhaupt von den Mahlscheiben erfasst wurden. Dabei etwas unangenehm brenzliger Geruch. Für Arabica recht ergiebige Crema. Relativ hell. Es handelt sich aber nicht um eine frühe Blondphase, da kaum helle Flecken zu erkennen sind. Starker Röstgeschmack. Bitterstoffe vorhanden, aber erstaunlicherweise nicht unangenehm. Da bin ich sonst empfindlich. Erinnert an Tannnadeln. Alles ein wenig penetrant. Dieser Schweizer Kaffee versucht, italienischer zu sein als ganz Italien. Insgesamt aber gute Qualität. Gut verträglich, wenig Koffein, schlägt nicht auf den Magen oder die Blase. Wieder kaufen: Hm... Es war einen Versuch wert. Der völlig anders geartete Mauro Espresso Bar ist inzwischen mein Lieblingskaffee geworden, aber etwas Abwechslung schadet auch nicht. Der Ferrari ist mir etwas zu teuer... Eher schenken lassen als kaufen.",
        "Name": "Ferrari Napoli",
        "Packungsgröße": "250 Gramm",
        "Maschine": "Gaggia Roma/Gaggia Classic",
        "Gekauft am": "27. Januar",
        "MHD": "31.03.09",
        "Eigenschaften": "Geliefert im Papiersack, 3 Monate haltbar. Bei den Ventilbeuteln habe ich jeweils den Eindruck, dass der Kaffee nach 1 oder 2 Tagen in der Mühle noch etwas aufblüht. Der Ferrari hatte nun also schon fast einen Monat Zeit, um in der Papiertüte \"aufzublühen\". Vielleicht ist das etwas lang, aber ich habe keine Vergleichsmöglichkeit mit frisch Geröstetem. Nun zum Kaffee selbst: Fast schwarz geröstete Arabica-Bohnen mit dicker Oelschicht. Klebrig. Ich brauchte einige Versuche, bis die Bohnen überhaupt von den Mahlscheiben erfasst wurden. Dabei etwas unangenehm brenzliger Geruch. Für Arabica recht ergiebige Crema. Relativ hell. Es handelt sich aber nicht um eine frühe Blondphase, da kaum helle Flecken zu erkennen sind. Starker Röstgeschmack. Bitterstoffe vorhanden, aber erstaunlicherweise nicht unangenehm. Da bin ich sonst empfindlich. Erinnert an Tannnadeln. Alles ein wenig penetrant. Dieser Schweizer Kaffee versucht, italienischer zu sein als ganz Italien. Insgesamt aber gute Qualität. Gut verträglich, wenig Koffein, schlägt nicht auf den Magen oder die Blase.",
        "Geschmack": "",
        "Wiederkaufen": "Hm... Es war einen Versuch wert. Der völlig anders geartete Mauro Espresso Bar ist inzwischen mein Lieblingskaffee geworden, aber etwas Abwechslung schadet auch nicht. Der Ferrari ist mir etwas zu teuer... Eher schenken lassen als kaufen."
    },
    {
        "Full Post": "AW: Ich trinke gerade diesen Espresso.... Name der Bohne: LAZZARIN Packungsgröße: 1000 Gramm Gemahlen und Bezogen mit: Mazzer Mini e, La Cimbali Junior S/1 Gekauft am: Mitte Januar 2009 MHD: Januar 2011 Eigenschaften: Einstellung des Mahlgrads nach 30 g sehr stabil. Hoher Robusta Anteil von 80%. Crema geht nicht besser. Super für Cappuccino. Magenfreundlich und sehr gute Verträglichkeit. Sehr unkomplizierter Kaffee. Wieder kaufen: Ja.",
        "Name": "LAZZARIN",
        "Packungsgröße": "1000 Gramm",
        "Maschine": "Mazzer Mini e, La Cimbali Junior S/1",
        "Gekauft am": "Mitte Januar 2009",
        "MHD": "Januar 2011",
        "Eigenschaften": "Einstellung des Mahlgrads nach 30 g sehr stabil. Hoher Robusta Anteil von 80%. Crema geht nicht besser. Super für Cappuccino. Magenfreundlich und sehr gute Verträglichkeit. Sehr unkomplizierter Kaffee.",
        "Geschmack": "",
        "Wiederkaufen": "Ja."
    },
    {
        "Full Post": "AW: Ich trinke gerade diesen Espresso.... Name der Bohne: Marcafè Crema Bar Super Packungsgröße: 1000 Gramm Gemahlen und Bezogen mit: Quickmill/Poccino 0835 Gekauft am: Mitte Januar 2009 MHD: Januar 2011 Eigenschaften: Laut Angabe 50/50 Arabica/Robusta. Einstellen der Mühle war nicht nötig, Durchlaufzeit passte sofort. Reichlich schöne dunkle Crema. Ich bin allerdings enttäuscht. Ich habe jetzt die Hälfte der Packung durch und von einem 50% Robusta hätte ich mehr Bums erwartet. Leicht malziger Geschmack, aber das Ergebnis ist sehr dünn. Als Espresso ok, nichts aufregendes, jedoch geht er im Cappu komplett unter. Kommentar meiner Frau : \" Carokaffee ? \".... Wieder kaufen: eher nicht",
        "Name": "Marcafè Crema Bar Super",
        "Packungsgröße": "1000 Gramm",
        "Maschine": "Quickmill/Poccino 0835",
        "Gekauft am": "Mitte Januar 2009",
        "MHD": "Januar 2011",
        "Eigenschaften": "Laut Angabe 50/50 Arabica/Robusta. Einstellen der Mühle war nicht nötig, Durchlaufzeit passte sofort. Reichlich schöne dunkle Crema. Ich bin allerdings enttäuscht. Ich habe jetzt die Hälfte der Packung durch und von einem 50% Robusta hätte ich mehr Bums erwartet. Leicht malziger , aber das Ergebnis ist sehr dünn. Als Espresso ok, nichts aufregendes, jedoch geht er im Cappu komplett unter. Kommentar meiner Frau : \" Carokaffee ? \"....",
        "Geschmack": "",
        "Wiederkaufen": "eher nicht"
    },
    {
        "Full Post": "AW: Ich trinke gerade diesen Espresso.... Name der Bohne: La Brasiliana Spezial Marfisa Packungsgröße: 1000 Gramm Gekauft am: Anfang Februar MHD: 24.06.10 Gemahlen und Bezogen mit: BFC Perfetta / K3 Eigenschaften: 24.11.08 steht noch drauf.(Röstdatum?) Laut Angabe 100% Arabica Feiner Mahlgrad. Viel Crema. Sehr fest und von schöner Konsistenz. Schön dunkle gemaserte Farbe. Duft der Bohne:Hmm.. Duft der gemahlen Bohne: Fantastisch. Geschmack: 9 Gramm im BFC-Einer - Nussartig mit leichter Schokoladennote. Vielfältige leichte andere Nuancen riech- und schmeckbar. Fantastisch. Nicht bitter und nicht sauer. Elegant mild und doch sehr intensiv. Mit Abstand der beste Espresso den ich hatte. (Von zirka 30 Sorten) P.s Muss aber noch einige probieren. Wieder kaufen: Ja, ja, ja",
        "Name": "La Brasiliana Spezial Marfisa",
        "Packungsgröße": "1000 Gramm",
        "Maschine": "BFC Perfetta / K3",
        "Gekauft am": "Anfang Februar",
        "MHD": "24.06.10",
        "Eigenschaften": "24.11.08 steht noch drauf.(Röstdatum?) Laut Angabe 100% Arabica Feiner Mahlgrad. Viel Crema. Sehr fest und von schöner Konsistenz. Schön dunkle gemaserte Farbe. Duft der Bohne:Hmm.. Duft der gemahlen Bohne: Fantastisch.",
        "Geschmack": "9 Gramm im BFC-Einer - Nussartig mit leichter Schokoladennote. Vielfältige leichte andere Nuancen riech- und schmeckbar. Fantastisch. Nicht bitter und nicht sauer. Elegant mild und doch sehr intensiv. Mit Abstand der beste Espresso den ich hatte. (Von zirka 30 Sorten) P.s Muss aber noch einige probieren.",
        "Wiederkaufen": "Ja, ja, ja"
    },
    {
        "Full Post": "AW: Ich trinke gerade diesen Espresso.... Name der Bohne: Marcafè Diamante Special Bar Packungsgröße: 1000 Gramm Gemahlen und Bezogen mit: Quickmill/Poccino 0835 Gekauft am: Mitte Januar 2009 MHD: Januar 2011 Eigenschaften: Laut Angabe 60/40 Arabica/Robusta. Der mag es sehr fein gemahlen. Nach kurzem Einstellen läuft er ganz gut. Dunkle Röstung, das Ergebnis ist aber nicht unbedingt kräftig. Das ist nun der zweite Marcafe den ich probiere und finde beide etwas schwach. Das mag auch an meinem Geschmack liegen. Als Espresso ist er in Ordnung, sehr mild. Für milchhaltige Getränke eher nicht geeignet, da geht auch dieser komplett unter. Wieder kaufen: Ich nicht. Wer auf der Suche nach einem milden Espresso ist, kann es natürlich probieren.",
        "Name": "Marcafè Diamante Special Bar",
        "Packungsgröße": "1000 Gramm",
        "Maschine": "Quickmill/Poccino 0835",
        "Gekauft am": "Mitte Januar 2009",
        "MHD": "Januar 2011",
        "Eigenschaften": "Laut Angabe 60/40 Arabica/Robusta. Der mag es sehr fein gemahlen. Nach kurzem Einstellen läuft er ganz gut. Dunkle Röstung, das Ergebnis ist aber nicht unbedingt kräftig. Das ist nun der zweite Marcafe den ich probiere und finde beide etwas schwach. Das mag auch an meinem  liegen. Als Espresso ist er in Ordnung, sehr mild. Für milchhaltige Getränke eher nicht geeignet, da geht auch dieser komplett unter.",
        "Geschmack": "",
        "Wiederkaufen": "Ich nicht. Wer auf der Suche nach einem milden Espresso ist, kann es natürlich probieren."
    },
    {
        "Full Post": "AW: Ich trinke gerade diesen Espresso.... Name der Bohne: IZZO 100% Arabica Gold Packungsgröße: 250 Gramm Gekauft am: Anfang Februar MHD: 11.09.11 Gemahlen und Bezogen mit: BFC Perfetta / K3 Eigenschaften: 08.09.08 (Röstdatum?) Laut Angabe 100% Arabica Grober Mahlgrad. Schöne dunkle Crema. Nicht sonderlich dick aber auch nicht dünn. Duft der Bohne: Gediegen.. Duft der gemahlen Bohne: Facettenreich. Geschmack: 9 Gramm im BFC-Einer - Bin wohl leicht zu begeistern. Setzt dem Spezial Marfisa noch eins drauf. Unglaublich blumiger edler Duft des bezogenen Espressos. Geschmack: Nuss mit vielfältigen Nuancen. Meine da auch ein wenig Minze zu verspüren. Schwer zu beschreiben. Unglaublich gut. Sehr aromatisch ohne aufdringlich zu sein. Kommt meiner Vorstellung eines richtig guten Espressos sehr nahe. Wieder kaufen: Ja, hat mich überzeugt. Gerade mit der Möglichkeit in in der 250 Gramm Dose zu ordern. Worin er scheinbar erst nach dem öffnen altert. 24 Stunden vorher öffnen kann ich bestätigen. (Öffnen und Deckel drauf)",
        "Name": "IZZO 100% Arabica Gold",
        "Packungsgröße": "250 Gramm",
        "Maschine": "BFC Perfetta / K3",
        "Gekauft am": "Anfang Februar",
        "MHD": "11.09.11",
        "Eigenschaften": "08.09.08 (Röstdatum?) Laut Angabe 100% Arabica Grober Mahlgrad. Schöne dunkle Crema. Nicht sonderlich dick aber auch nicht dünn. Duft der Bohne: Gediegen.. Duft der gemahlen Bohne: Facettenreich.",
        "Geschmack": "9 Gramm im BFC-Einer - Bin wohl leicht zu begeistern. Setzt dem Spezial Marfisa noch eins drauf. Unglaublich blumiger edler Duft des bezogenen Espressos.",
        "Wiederkaufen": "Ja, hat mich überzeugt. Gerade mit der Möglichkeit in in der 250 Gramm Dose zu ordern. Worin er scheinbar erst nach dem öffnen altert. 24 Stunden vorher öffnen kann ich bestätigen. (Öffnen und Deckel drauf)"
    },
    {
        "Full Post": "AW: Ich trinke gerade diesen Espresso.... Name der Bohne: Böhm Kaffee Espresso, Hausmarke Feinkost Böhm Stuttgart Packungsgröße: 250 Gramm, Aromaventil:lol: Gemahlen und Bezogen mit: s. Signatur Gekauft am: 31.01.2009 MHD: 15.07.2009 MHD in Monaten: 6 Eigenschaften: Dunkelbraune, durchaus stabile Crema, feiner würziger Duft. Geschmack: Leicht fruchtige, säurebetonte Note, schlanker Körper, wenig Nachgeschmack beim Abgang. Als Cappuccino eher ungeeignet. Herstellerangaben: schonende Langzeitröstung in kleinen Partien, verpackt in speziellen Aromaventiltüten Wieder kaufen: Jein, für Espresso ja, für Cappu nein.",
        "Name": "Böhm Kaffee Espresso, Hausmarke Feinkost Böhm Stuttgart",
        "Packungsgröße": "250 Gramm, Aromaventil:lol:",
        "Maschine": "s. Signatur",
        "Gekauft am": "31.01.2009",
        "MHD": "15.07.2009  in Monaten: 6",
        "Eigenschaften": "Dunkelbraune, durchaus stabile Crema, feiner würziger Duft.",
        "Geschmack": "Leicht fruchtige, säurebetonte Note, schlanker Körper, wenig Nachgeschmack beim Abgang. Als Cappuccino eher ungeeignet. Herstellerangaben: schonende Langzeitröstung in kleinen Partien, verpackt in speziellen Aromaventiltüten",
        "Wiederkaufen": "Jein, für Espresso ja, für Cappu nein."
    },
    {
        "Full Post": "AW: Ich trinke gerade diesen Espresso.... Zitat von Determann: ↑ Name der Bohne: Böhm Kaffee Espresso, Hausmarke Feinkost Böhm Stuttgart Packungsgröße: 250 Gramm, Aromaventil:lol: Gemahlen und Bezogen mit: s. Signatur Gekauft am: 31.01.2009 MHD: 15.07.2009 MHD in Monaten: 6 Eigenschaften: Dunkelbraune, durchaus stabile Crema, feiner würziger Duft. Geschmack: Leicht fruchtige, säurebetonte Note, schlanker Körper, wenig Nachgeschmack beim Abgang. Als Cappuccino eher ungeeignet. Herstellerangaben: schonende Langzeitröstung in kleinen Partien, verpackt in speziellen Aromaventiltüten Wieder kaufen: Jein, für Espresso ja, für Cappu nein. Klicke in dieses Feld, um es in vollständiger Größe anzuzeigen. Und warum bist Du so laut? ;-)",
        "Name": "Böhm Kaffee Espresso, Hausmarke Feinkost Böhm Stuttgart",
        "Packungsgröße": "250 Gramm, Aromaventil:lol:",
        "Maschine": "s. Signatur",
        "Gekauft am": "31.01.2009",
        "MHD": "15.07.2009  in Monaten: 6",
        "Eigenschaften": "Dunkelbraune, durchaus stabile Crema, feiner würziger Duft.",
        "Geschmack": "Leicht fruchtige, säurebetonte Note, schlanker Körper, wenig Nachgeschmack beim Abgang. Als Cappuccino eher ungeeignet. Herstellerangaben: schonende Langzeitröstung in kleinen Partien, verpackt in speziellen Aromaventiltüten",
        "Wiederkaufen": "Jein, für Espresso ja, für Cappu nein. Klicke in dieses Feld, um es in vollständiger Größe anzuzeigen. Und warum bist Du so laut? ;-)"
    },
    {
        "Full Post": "Name der Bohne: Böhm Kaffee Espresso, Hausmarke Feinkost Böhm Stuttgart Packungsgröße: 250 Gramm, Aromaventil:lol: Gemahlen und Bezogen mit: s. Signatur Gekauft am: 31.01.2009 MHD: 15.07.2009 MHD in Monaten: 6 Eigenschaften: Dunkelbraune, durchaus stabile Crema, feiner würziger Duft. Geschmack: Leicht fruchtige, säurebetonte Note, schlanker Körper, wenig Nachgeschmack beim Abgang. Als Cappuccino eher ungeeignet. Herstellerangaben: schonende Langzeitröstung in kleinen Partien, verpackt in speziellen Aromaventiltüten Wieder kaufen: Jein, für Espresso ja, für Cappu nein. Klicke in dieses Feld, um es in vollständiger Größe anzuzeigen.",
        "Name": "Böhm Kaffee Espresso, Hausmarke Feinkost Böhm Stuttgart",
        "Packungsgröße": "250 Gramm, Aromaventil:lol:",
        "Maschine": "s. Signatur",
        "Gekauft am": "31.01.2009",
        "MHD": "15.07.2009  in Monaten: 6",
        "Eigenschaften": "Dunkelbraune, durchaus stabile Crema, feiner würziger Duft.",
        "Geschmack": "Leicht fruchtige, säurebetonte Note, schlanker Körper, wenig Nachgeschmack beim Abgang. Als Cappuccino eher ungeeignet. Herstellerangaben: schonende Langzeitröstung in kleinen Partien, verpackt in speziellen Aromaventiltüten",
        "Wiederkaufen": "Jein, für Espresso ja, für Cappu nein. Klicke in dieses Feld, um es in vollständiger Größe anzuzeigen."
    },
    {
        "Full Post": "AW: Ich trinke gerade diesen Espresso.... Name der Bohne: Fausto Giasing Packungsgröße: 250 Gramm, Aromaventil Gemahlen und Bezogen mit: Bezzera 105/Cimbali M30 Gekauft am: Ende Januar Geröstet: 27.01.2009 MHD in Monaten: wirds nicht erleben. Eigenschaften: Zunächst: Schon alle. Noch immer alle Angaben unter Vorbehalt: Ich und die Cimbali lernen einander kennen. Erschwerend kommt hinzu, dass in das Sieb kaum 14 Gramm reinpassen, außer meine Waage ist so derangiert, dass es nicht stimmt. Zumindest muss ich echt voll packen, damit es was wird. Also, der Giasing hat zur Erholung ja mal ein wenig Robusta gehabt. Schöne Crema, aber nicht monströs wie Barschlampen. Schokolade und feine Säure (die ich wie immer eigentlich nicht so mag). Insgesamt für diejenigen, die neben Robusta-Crema und Schokolade vielleicth auch ein wenig Säure suchen exakt das richtige. Wieder kaufen? Ich nicht. Ist aber für mich keine Frage der Qualität, sondern des Geschmacks.",
        "Name": "Fausto Giasing",
        "Packungsgröße": "250 Gramm, Aromaventil",
        "Maschine": "Bezzera 105/Cimbali M30",
        "Gekauft am": "Ende Januar Geröstet: 27.01.2009  in Monaten: wirds nicht erleben.",
        "MHD": "",
        "Eigenschaften": "",
        "Geschmack": "",
        "Wiederkaufen": ""
    },
    {
        "Full Post": "AW: Ich trinke gerade diesen Espresso.... Gerade ausgetrunken Name der Bohne: Brao Mrs. Rose Packungsgröße: 250 Gramm Dose Gemahlen und Bezogen mit: s. Signatur Gekauft am: 15.01.2009 MHD: 04.2010 MHD in Monaten: - Eigenschaften: Mittelbraune Crema, nicht allzu stabil. Geschmack: Feine Fruchtnote, leicht säurebetont, mittlerer Körper, sehr angenehm zu trinken, kurzer Nachgeschmack beim Abgang. Auch als Cappuccino ok, als Espresso gut. Besondere Herstellerangaben: Koffeingehalt 1,31 % Wieder kaufen: Ja bei Gelegenheit, aber nicht vorrangig.",
        "Name": "Brao Mrs. Rose",
        "Packungsgröße": "250 Gramm Dose",
        "Maschine": "s. Signatur",
        "Gekauft am": "15.01.2009",
        "MHD": "04.2010  in Monaten: -",
        "Eigenschaften": "Mittelbraune Crema, nicht allzu stabil.",
        "Geschmack": "Feine Fruchtnote, leicht säurebetont, mittlerer Körper, sehr angenehm zu trinken, kurzer Nachgeschmack beim Abgang. Auch als Cappuccino ok, als Espresso gut. Besondere Herstellerangaben: Koffeingehalt 1,31 %",
        "Wiederkaufen": "Ja bei Gelegenheit, aber nicht vorrangig."
    },
    {
        "Full Post": "AW: Ich trinke gerade diesen Espresso.... Gerade am Trinken Name der Bohne: Diemme Oro (Blue) Laut kaffeezentrale identisch mit Oro Packungsgröße: 250 Gramm Dose, blau Gemahlen und Bezogen mit: s. Signatur Gekauft am: 20.02.2009 MHD: 06.2010 MHD in Monaten: 18 Eigenschaften: Dunkelbraune üppige Crema, stabil ohne Ende, Tragkraft wahrscheinlich 1 kg Zucker / qcm:lol: Für einen reinen Arabica die reinste Monstercrema :lol: Geschmack: Kräftige Schokonote, wenig Säure, mächtiger Körper, sehr ausgewogen, keine hervorstechenden Geschmacksnuancen, unglaublich lang anhaltender Nachgeschmack beim Abgang. Bis jetzt nur als Espresso probiert, hier ausgezeichnet. Anmerkungen: Läuft unwahrscheinlich cremig und dunkel aus dem Auslauf, in der Anwendung unproblematisch, Ergebnis in der Tasse sehr konstant. Wieder kaufen: Ja, definitiv!",
        "Name": "Diemme Oro (Blue) Laut kaffeezentrale identisch mit Oro",
        "Packungsgröße": "250 Gramm Dose, blau",
        "Maschine": "s. Signatur",
        "Gekauft am": "20.02.2009",
        "MHD": "06.2010  in Monaten: 18",
        "Eigenschaften": "Dunkelbraune üppige Crema, stabil ohne Ende, Tragkraft wahrscheinlich 1 kg Zucker / qcm:lol: Für einen reinen Arabica die reinste Monstercrema :lol:",
        "Geschmack": "Kräftige Schokonote, wenig Säure, mächtiger Körper, sehr ausgewogen, keine hervorstechenden snuancen, unglaublich lang anhaltender Nachgeschmack beim Abgang. Bis jetzt nur als Espresso probiert, hier ausgezeichnet. Anmerkungen: Läuft unwahrscheinlich cremig und dunkel aus dem Auslauf, in der Anwendung unproblematisch, Ergebnis in der Tasse sehr konstant.",
        "Wiederkaufen": "Ja, definitiv!"
    },
    {
        "Full Post": "AW: Ich trinke gerade diesen Espresso.... Name der Bohne: Ethiopia Sidamo von Caffé Fausto Packungsgröße: 250 Gramm Gemahlen und Bezogen mit: Iberital Challenge / Gaggia Baby Class Gekauft am: Lieferung erfolgte am 21. Februar MHD: 02/10 (geröstet am 12.02.) Eigenschaften: Der Sidamo ist nicht ganz so einfach zu handhaben wie der Giasing oder der Malabar (obwohl ich mit meiner letzten Malabar-Lieferung im Dezember komischerweise mehr Probleme hatte). Als zickig würde ich ihn jedoch nicht bezeichnen. Der Mahlgrad ist bei mir wesentlich gröber wie bei den oben genannten Sorten. Nach 3-4 Shots stimmten die Parameter und heraus kam ein Espresso mit Bilderbuch-Crema, leichten Säure-Noten und langem Nachgeschmack. Eine Crema-Bombe wir der Malabar ist er jedoch nicht. Meinem Empfinden nach hat er auch nicht ganz so einen vollen Körper wie der Malaber. Trotzdem sehr lecker und eine nette Abwechslung. Da ich Espresso bevorzugt mit Zucker trinke, auch hier ein Unterschied: während ich meine Lieblingssorten Giasing und Malabar fast nur noch mit dem Billington Light Muscovado trinke, schmeckt mir der Sidamo mit normalen weißen Zucker besser. Wieder kaufen: Ja!",
        "Name": "Ethiopia Sidamo von Caffé Fausto",
        "Packungsgröße": "250 Gramm",
        "Maschine": "Iberital Challenge / Gaggia Baby Class",
        "Gekauft am": "Lieferung erfolgte am 21. Februar",
        "MHD": "02/10 (geröstet am 12.02.)",
        "Eigenschaften": "Der Sidamo ist nicht ganz so einfach zu handhaben wie der Giasing oder der Malabar (obwohl ich mit meiner letzten Malabar-Lieferung im Dezember komischerweise mehr Probleme hatte). Als zickig würde ich ihn jedoch nicht bezeichnen. Der Mahlgrad ist bei mir wesentlich gröber wie bei den oben genannten Sorten. Nach 3-4 Shots stimmten die Parameter und heraus kam ein Espresso mit Bilderbuch-Crema, leichten Säure-Noten und langem Nachgeschmack. Eine Crema-Bombe wir der Malabar ist er jedoch nicht. Meinem Empfinden nach hat er auch nicht ganz so einen vollen Körper wie der Malaber. Trotzdem sehr lecker und eine nette Abwechslung. Da ich Espresso bevorzugt mit Zucker trinke, auch hier ein Unterschied: während ich meine Lieblingssorten Giasing und Malabar fast nur noch mit dem Billington Light Muscovado trinke, schmeckt mir der Sidamo mit normalen weißen Zucker besser.",
        "Geschmack": "",
        "Wiederkaufen": "Ja!"
    },
    {
        "Full Post": "AW: Ich trinke gerade diesen Espresso.... Gerade am Trinken Name der Bohne: Izzo Gold Kaffee Espresso - 100% Arabica Packungsgröße: 250 Gramm Dose Gemahlen und Bezogen mit: s. Signatur Gekauft am: 20.02.2009 MHD: 11.09.2011 MHD in Monaten: 36 Eigenschaften: Mittelbraune, geschlossene Crema, wenig stabil. Geschmack: Sehr samtig, sehr weich, keine besonderen Geschmacksnuancen erkennbar, keinerlei Nachgeschmack beim Abgang. Für Cappu völlig ungeeignet. Als Espresso ausreichend. Anmerkungen: Hatte mir mehr von dem Kaffee erwartet, war von dem Izzo Silver sehr angetan, schade. Habe mir sehr viel Mühe gegeben mit Mahlgrad und Menge, die theoretischen Parameter haben gestimmt, leider war das Ergebnis in der Tasse nur ausreichend. Wieder kaufen: Nein.",
        "Name": "Izzo Gold Kaffee Espresso - 100% Arabica",
        "Packungsgröße": "250 Gramm Dose",
        "Maschine": "s. Signatur",
        "Gekauft am": "20.02.2009",
        "MHD": "11.09.2011  in Monaten: 36",
        "Eigenschaften": "Mittelbraune, geschlossene Crema, wenig stabil.",
        "Geschmack": "Sehr samtig, sehr weich, keine besonderen snuancen erkennbar, keinerlei Nachgeschmack beim Abgang. Für Cappu völlig ungeeignet. Als Espresso ausreichend. Anmerkungen: Hatte mir mehr von dem Kaffee erwartet, war von dem Izzo Silver sehr angetan, schade. Habe mir sehr viel Mühe gegeben mit Mahlgrad und Menge, die theoretischen Parameter haben gestimmt, leider war das Ergebnis in der Tasse nur ausreichend.",
        "Wiederkaufen": "Nein."
    },
    {
        "Full Post": "AW: Ich trinke gerade diesen Espresso.... Gerade am Trinken: Name der Bohne: Izzo Supermiscela Bar aka Izzo Silver in der 250 g Dose Packungsgröße: 250 Gramm Dose Gemahlen und Bezogen mit: La San Marco 85E Practical, Macap M4D digital stepless Gekauft am: 20.02.2009 MHD: 17.10.2011 MHD in Monaten: 36 Eigenschaften: Dunkelbraune, geschlossene Crema, sehr stabil, sehr schönes gleichmäßiges Bohnenbild, Bohnen glänzen dunkel ölig. Geschmack: Sehr cremig, voller, angenehmer Schoko-Geschmack, keine Bittertöne, lang anhaltender Nachgeschmack beim Abgang, nicht sauer. Kommt auch im Cappu voll zur Geltung. Anmerkungen: Erfüllt meine Erwartungen an lecker Espresso in hohem Maße, bei sehr feinem Mahlgrad läuft der Kaffee dunkel, ölig in die Tasse. Verträgt etwas längere Bezugsdauer von mehr als 25 Sekunden. Sehr einfach anzuwenden, sowohl im 1-er, wie auch im 2-er Sieb. Konstante Ergebnisse möglich. Fazit: Klasse, *** stars out of five Wieder kaufen: Jederzeit:lol: Gruß Determann",
        "Name": "Izzo Supermiscela Bar aka Izzo Silver in der 250 g Dose",
        "Packungsgröße": "250 Gramm Dose",
        "Maschine": "La San Marco 85E Practical, Macap M4D digital stepless",
        "Gekauft am": "20.02.2009",
        "MHD": "17.10.2011  in Monaten: 36",
        "Eigenschaften": "Dunkelbraune, geschlossene Crema, sehr stabil, sehr schönes gleichmäßiges Bohnenbild, Bohnen glänzen dunkel ölig.",
        "Geschmack": "Sehr cremig, voller, angenehmer Schoko-, keine Bittertöne, lang anhaltender Nachgeschmack beim Abgang, nicht sauer. Kommt auch im Cappu voll zur Geltung. Anmerkungen: Erfüllt meine Erwartungen an lecker Espresso in hohem Maße, bei sehr feinem Mahlgrad läuft der Kaffee dunkel, ölig in die Tasse. Verträgt etwas längere Bezugsdauer von mehr als 25 Sekunden. Sehr einfach anzuwenden, sowohl im 1-er, wie auch im 2-er Sieb. Konstante Ergebnisse möglich. Fazit: Klasse, *** stars out of five",
        "Wiederkaufen": "Jederzeit:lol: Gruß Determann"
    },
    {
        "Full Post": "AW: Ich trinke gerade diesen Espresso.... Name der Bohne: Flor de Marcala von Caffé Fausto Packungsgröße: 250 Gramm Gemahlen und Bezogen mit: Iberital Challenge / Gaggia Baby Class Gekauft am: Lieferung erfolgte am 21. Februar MHD: 02/10 (geröstet am 12.02.) Eigenschaften: Der Flor de Marcala ist ein weiterer wirklich toller Espresso aus dem Hause Fausto! Die Handhabung ist auch wie beim Sidamo nicht ganz einfach; zumindest verzeiht er bei mir nicht die geringsten Fehler; schon minimale Abweichung von den optimalen Parametern führt dazu, das z.B. keine Crema vorhanden ist bzw. das diese sofort aufreisst. Wenn man jedoch am Ball bleibt, wird man mit einem wunderbaren Espresso belohnt, der mild, aber gleichzeitig vollmundig schmeckt, dabei leichte Säurenoten entfaltet (ganz gefährlich bei mir, aber hier passt das Verhältnis), ohne sauer zu werden und dessen Aroma lange erhalten bleibt. Mir fällt es immer noch schwer, die auftretenden Aromen treffend zu beschreiben, \"dergitarrist\" hat das in seinem Bericht aber vortrefflich getan; dem kann ich voll zustimmen. Leider sind die 250gr. bald alle, doch bei der nächsten Bestellung werde ich den Marcala wieder ordern. Er ist in meinen Augen eine tolle Alternative zu den recht \"wuchtigen\" Sorten wie Giasing oder Malabar, die ich sonst bevorzuge. Wieder kaufen: Ja!",
        "Name": "Flor de Marcala von Caffé Fausto",
        "Packungsgröße": "250 Gramm",
        "Maschine": "Iberital Challenge / Gaggia Baby Class",
        "Gekauft am": "Lieferung erfolgte am 21. Februar",
        "MHD": "02/10 (geröstet am 12.02.)",
        "Eigenschaften": "Der Flor de Marcala ist ein weiterer wirklich toller Espresso aus dem Hause Fausto! Die Handhabung ist auch wie beim Sidamo nicht ganz einfach; zumindest verzeiht er bei mir nicht die geringsten Fehler; schon minimale Abweichung von den optimalen Parametern führt dazu, das z.B. keine Crema vorhanden ist bzw. das diese sofort aufreisst. Wenn man jedoch am Ball bleibt, wird man mit einem wunderbaren Espresso belohnt, der mild, aber gleichzeitig vollmundig schmeckt, dabei leichte Säurenoten entfaltet (ganz gefährlich bei mir, aber hier passt das Verhältnis), ohne sauer zu werden und dessen Aroma lange erhalten bleibt. Mir fällt es immer noch schwer, die auftretenden Aromen treffend zu beschreiben, \"dergitarrist\" hat das in seinem Bericht aber vortrefflich getan; dem kann ich voll zustimmen. Leider sind die 250gr. bald alle, doch bei der nächsten Bestellung werde ich den Marcala wieder ordern. Er ist in meinen Augen eine tolle Alternative zu den recht \"wuchtigen\" Sorten wie Giasing oder Malabar, die ich sonst bevorzuge.",
        "Geschmack": "",
        "Wiederkaufen": "Ja!"
    },
    {
        "Full Post": "AW: Ich trinke gerade diesen Espresso.... Name der Bohne: Olivier No. 1 Packungsgröße: 250 Gramm Gemahlen und Bezogen mit: Rocky / Silvia Gekauft am: 2.04.09 Geröstet am: 31.03.09 MHD: 31.03.2010 Eigenschaften: Es gibt ja schon einige Charakterisierungen. Ich möchte hier auf den schmalen Grad des Gelingens eingehen. Liegt es an der Frische, oder an der Bohne? Ich bewege mich bei der Rocky zwischen 2 Mahlstufen. Bei der gröberen Stufe schießen die 25 / 50ml in 12-15 Sekunden in die Tasse (gilt sowohl für 1-er-LM uns 2-er-Orignal-Sieb), bei der feineren Stufe quälen sich in 25 Sekunden ca. 15 / 30ml in die Tasse. Crema und Geschmack in der feineren Variante deutlich runder. Ich bin noch ein relativer Anfänger - aber mit den Fausto-Sorten Malabar, Flor de Marcala, Giasing und Peru hatte ich diese Probleme nicht! :roll: Nach meinem Empfinden mag es die No.1 eher nicht ganz so heiß. Habe ich bei den Fauso-Sorten immer 20-30 Sekunden nach dem Erlöschen der Aufheizlampe gewartet, bevor der Bezug gestartet wurde, mag es No.1 am Liebsten direkt nach Erlöschen der Lampe - sonst wird man mit einer leicht verbrannten Note abgemahnt. Wieder kaufen: Wenn ich ihn irgendwann doch noch in den Griff bekomme vielleicht, Potential + Charakter hat er! Gruß in die Runde von, Erik",
        "Name": "Olivier No. 1",
        "Packungsgröße": "250 Gramm",
        "Maschine": "Rocky / Silvia",
        "Gekauft am": "2.04.09 Geröstet am: 31.03.09",
        "MHD": "31.03.2010",
        "Eigenschaften": "Es gibt ja schon einige Charakterisierungen. Ich möchte hier auf den schmalen Grad des Gelingens eingehen. Liegt es an der Frische, oder an der Bohne? Ich bewege mich bei der Rocky zwischen 2 Mahlstufen. Bei der gröberen Stufe schießen die 25 / 50ml in 12-15 Sekunden in die Tasse (gilt sowohl für 1-er-LM uns 2-er-Orignal-Sieb), bei der feineren Stufe quälen sich in 25 Sekunden ca. 15 / 30ml in die Tasse. Crema und  in der feineren Variante deutlich runder. Ich bin noch ein relativer Anfänger - aber mit den Fausto-Sorten Malabar, Flor de Marcala, Giasing und Peru hatte ich diese Probleme nicht! :roll: Nach meinem Empfinden mag es die No.1 eher nicht ganz so heiß. Habe ich bei den Fauso-Sorten immer 20-30 Sekunden nach dem Erlöschen der Aufheizlampe gewartet, bevor der Bezug gestartet wurde, mag es No.1 am Liebsten direkt nach Erlöschen der Lampe - sonst wird man mit einer leicht verbrannten Note abgemahnt.",
        "Geschmack": "",
        "Wiederkaufen": "Wenn ich ihn irgendwann doch noch in den Griff bekomme vielleicht, Potential + Charakter hat er! Gruß in die Runde von, Erik"
    },
    {
        "Full Post": "AW: Ich trinke gerade diesen Espresso.... Name der Bohne: Splendid Oro Packungsgröße: 1000 Gramm Gemahlen und Bezogen mit: Faema MPN/Faema Compact Gekauft am: Anfang April MHD: 12/09 Eigenschaften: Schmeckt einfach nur SUPER!!!!! Wiederkaufen: ja ja ja ja ja ja......",
        "Name": "Splendid Oro",
        "Packungsgröße": "1000 Gramm",
        "Maschine": "Faema MPN/Faema Compact",
        "Gekauft am": "Anfang April",
        "MHD": "12/09",
        "Eigenschaften": "",
        "Geschmack": "",
        "Wiederkaufen": ""
    },
    {
        "Full Post": "AW: Ich trinke gerade diesen Espresso.... Name der Bohne: Yirgacheffe von der Kaffeezeremonie ​ Packungsgröße: 1000 Gramm​ Gemahlen und Bezogen mit: Mazzer Mini B | Vibiemme Domobar​ Gekauft am: gestern​ MHD: 12/09​ Eigenschaften: Kräftige Bohne, relativ dunkel geröstet, starker aber sehr ausgewogener Espresso, keine Säure, keine Bitterstoffe | mein momentaner Favorit​ Wieder kaufen: auf jeden Fall​ Mischung, Sonstiges: 100% Arabica | etwas anderes kommt für Äthiopier nicht in Frage | der Besitzer des Ladens importiert direkt von Bauern aus Äthiopien | zu bestellen übers Internet.​",
        "Name": "Yirgacheffe von der Kaffeezeremonie ​",
        "Packungsgröße": "1000 Gramm​",
        "Maschine": "Mazzer Mini B | Vibiemme Domobar​",
        "Gekauft am": "gestern​",
        "MHD": "12/09​",
        "Eigenschaften": "Kräftige Bohne, relativ dunkel geröstet, starker aber sehr ausgewogener Espresso, keine Säure, keine Bitterstoffe | mein momentaner Favorit​",
        "Geschmack": "",
        "Wiederkaufen": "auf jeden Fall​ Mischung, Sonstiges: 100% Arabica | etwas anderes kommt für Äthiopier nicht in Frage | der Besitzer des Ladens importiert direkt von Bauern aus Äthiopien | zu bestellen übers Internet.​"
    },
    {
        "Full Post": "AW: Ich trinke gerade diesen Espresso.... Name der Bohne: Martella Maximum Class Packungsgröße: 250 Gramm Gemahlen und Bezogen mit: Compak K3/Bezzera GEA Gekauft am: 7.12.2009 MHD: 15/11/2011 90/10 Arabica/Robusta Eigenschaften: Sehr unkomplizierter Kaffee.Als Espresso super schokoladig und eine wahre Crema-Bombe(Kaffee ca.3 Wochen alt).Geschmacklich mit das Beste,was bei mir jemals in der Tasse gelandet ist. Wenn der Martella so frisch ist,hat er bei mir sogar gegenüber den Boardröstern die Nase vorn.(Kaffee-Total hat den Martella momentan sehr frisch). Wieder kaufen: Auf jeden Fall! Gruß Frank",
        "Name": "Martella Maximum Class",
        "Packungsgröße": "250 Gramm",
        "Maschine": "Compak K3/Bezzera GEA",
        "Gekauft am": "7.12.2009",
        "MHD": "15/11/2011 90/10 Arabica/Robusta",
        "Eigenschaften": "Sehr unkomplizierter Kaffee.Als Espresso super schokoladig und eine wahre Crema-Bombe(Kaffee ca.3 Wochen alt).lich mit das Beste,was bei mir jemals in der Tasse gelandet ist. Wenn der Martella so frisch ist,hat er bei mir sogar gegenüber den Boardröstern die Nase vorn.(Kaffee-Total hat den Martella momentan sehr frisch).",
        "Geschmack": "",
        "Wiederkaufen": "Auf jeden Fall! Gruß Frank"
    },
    {
        "Full Post": "AW: Ich trinke gerade diesen Espresso.... Name der Bohne: Klingler Monsooned Malabar Packungsgröße: 250 Gramm Gemahlen und Bezogen mit: Ascaso I.1 / La Spaziale Mini Vivaldi Gekauft am: Anfang Oktober MHD: 10/11 Eigenschaften: Wie viele Malabars muss er erst ein paar Tage liegen, da er frisch nach der Röstung sehr stark ausgast und schwer zu beherrschen ist. Die Tüten machen mächtig dicke Backen und würden ohne Ventil wahrscheinlich platzen. Im Espresso ist der Geschmack würzig, etwas erdig mit einem Hauch Bitterschokolade. Im Cappucino relativ unauffällig - geht fast etwas unter, die Milch dominiert. Die ersten Tage ist er etwas rauh - erweckt den Eindruck etwas Pfeffer in der Tasse zu haben. Nach einer Woche merklich runder. Die Crema ist fein, dennoch recht stabil und von schöner rötlich brauner Farbe. Die Temperatur liegt bei 95 Grad +/- (ich fahre einen Offset von +2 Grad). Nach dem Ausgasen ein relativ unkomplizierter Espresso. Wieder kaufen: Ja.",
        "Name": "Klingler Monsooned Malabar",
        "Packungsgröße": "250 Gramm",
        "Maschine": "Ascaso I.1 / La Spaziale Mini Vivaldi",
        "Gekauft am": "Anfang Oktober",
        "MHD": "10/11",
        "Eigenschaften": "Wie viele Malabars muss er erst ein paar Tage liegen, da er frisch nach der Röstung sehr stark ausgast und schwer zu beherrschen ist. Die Tüten machen mächtig dicke Backen und würden ohne Ventil wahrscheinlich platzen. Im Espresso ist der  würzig, etwas erdig mit einem Hauch Bitterschokolade. Im Cappucino relativ unauffällig - geht fast etwas unter, die Milch dominiert. Die ersten Tage ist er etwas rauh - erweckt den Eindruck etwas Pfeffer in der Tasse zu haben. Nach einer Woche merklich runder. Die Crema ist fein, dennoch recht stabil und von schöner rötlich brauner Farbe. Die Temperatur liegt bei 95 Grad +/- (ich fahre einen Offset von +2 Grad). Nach dem Ausgasen ein relativ unkomplizierter Espresso.",
        "Geschmack": "",
        "Wiederkaufen": "Ja."
    },
    {
        "Full Post": "AW: Ich trinke gerade diesen Espresso.... Name der Bohne: Mirella Espresso Malabar Packungsgröße: 500 Gramm Gemahlen und Bezogen mit: Demokam203/Ascaso Basic Gekauft am: Mitte Dezember MHD: Packung schon weg, war aber sehr frisch geröstet Eigenschaften: Sehr vielfältig. Je nach Mahlgrad von fruchtig süß bis schokoladig. Ich finde ihn wegen dieser Vielfältigkeit sehr gut. Eventuell hab ich ihn ein bisschen zu früh aufgemacht. Wieder kaufen: Ja",
        "Name": "Mirella Espresso Malabar",
        "Packungsgröße": "500 Gramm",
        "Maschine": "Demokam203/Ascaso Basic",
        "Gekauft am": "Mitte Dezember",
        "MHD": "Packung schon weg, war aber sehr frisch geröstet",
        "Eigenschaften": "Sehr vielfältig. Je nach Mahlgrad von fruchtig süß bis schokoladig. Ich finde ihn wegen dieser Vielfältigkeit sehr gut. Eventuell hab ich ihn ein bisschen zu früh aufgemacht.",
        "Geschmack": "",
        "Wiederkaufen": "Ja"
    },
    {
        "Full Post": "AW: Ich trinke gerade diesen Espresso.... Name der Bohne: Röstrei Schneid, München / Costa Rica Crire Tarrazu, 100% Arabica Packungsgröße: 250 Gramm im Folienbeutel (angepiekst, das Löchlein klebe mit Tesafilm zu, dann hält sich der Beutel sogar im Tiefkühler sehr gut, besser als zugeklebte Ventilbeutel) Gemahlen und Bezogen mit: Mazzer Kony u. Rancilio Handhebel Classe 6 Gekauft am: Mitte Feb. 2011 MHD: Ende 9/2011 Eigenschaften: Eher hell geröstet (mir immer sehr recht), muß auffallend fein gemahlen werden, schöner rotbrauner Farbton von Kaffeemehl (sieht überhaupt sehr frisch aus, wie feuchte, feine Erde, wenn ich getamped habe) und Crema. Brühtemperatur eher medium (nicht zu heiß, aber kein \"Kühlbrüher\"). Duft wie Zimt mit Nuss, als Espresso (8,8g auf ca. 15 ml? gehebelt) viel Marzipan und Nuss, angenehm frisch dabei durch leichte Fruchtigkeit im Hintergrund, ansonsten eher keine auffallende Säure (da freut sich ein empfindlicher Magen), würzig (wirklich etwas gewürzig), schöner u. ausgeprägter Körper, freundlicher Abgang - insgesamt ausgewogen und lecker. Geht auch im Cappu nicht unter, sollte aber nicht in Milch ertränkt werden - dann ergibt sich ein schöner tiefschokoladiger Espresso Macchiato. P.S.: Er ist nicht zickig (Mahlgrad etc.). Wieder kaufen:Ja",
        "Name": "Röstrei Schneid, München / Costa Rica Crire Tarrazu, 100% Arabica",
        "Packungsgröße": "250 Gramm im Folienbeutel (angepiekst, das Löchlein klebe mit Tesafilm zu, dann hält sich der Beutel sogar im Tiefkühler sehr gut, besser als zugeklebte Ventilbeutel)",
        "Maschine": "Mazzer Kony u. Rancilio Handhebel Classe 6",
        "Gekauft am": "Mitte Feb. 2011",
        "MHD": "Ende 9/2011",
        "Eigenschaften": "Eher hell geröstet (mir immer sehr recht), muß auffallend fein gemahlen werden, schöner rotbrauner Farbton von Kaffeemehl (sieht überhaupt sehr frisch aus, wie feuchte, feine Erde, wenn ich getamped habe) und Crema. Brühtemperatur eher medium (nicht zu heiß, aber kein \"Kühlbrüher\"). Duft wie Zimt mit Nuss, als Espresso (8,8g auf ca. 15 ml? gehebelt) viel Marzipan und Nuss, angenehm frisch dabei durch leichte Fruchtigkeit im Hintergrund, ansonsten eher keine auffallende Säure (da freut sich ein empfindlicher Magen), würzig (wirklich etwas gewürzig), schöner u. ausgeprägter Körper, freundlicher Abgang - insgesamt ausgewogen und lecker. Geht auch im Cappu nicht unter, sollte aber nicht in Milch ertränkt werden - dann ergibt sich ein schöner tiefschokoladiger Espresso Macchiato. P.S.: Er ist nicht zickig (Mahlgrad etc.).",
        "Geschmack": "",
        "Wiederkaufen": ""
    },
    {
        "Full Post": "AW: Ich trinke gerade diesen Espresso.... Name der Bohne: Espresso Turbo von der KFE Rösterei aus Lindau(Pfalz) Packungsgröße: 250 Gramm Gemahlen und Bezogen mit: Mod. Mokita PL 42 geröstet KW 46, Gekauft am: 19.11.2011 MHD: 19/11/2012 Eigenschaften: stabile Haselnuss braune Crema lebhafter würziger Kräftiger Espresso, keine säure. der Puck ist nach dem Bezug recht nass, liegt wohl auch noch an der frische der Bohnen. Wieder kaufen: Absolut ! Macht süchtig!!! Top/ Preis leistungsverhältnis!",
        "Name": "Espresso Turbo von der KFE Rösterei aus Lindau(Pfalz)",
        "Packungsgröße": "250 Gramm",
        "Maschine": "Mod. Mokita PL 42 geröstet KW 46,",
        "Gekauft am": "19.11.2011",
        "MHD": "19/11/2012",
        "Eigenschaften": "stabile Haselnuss braune Crema lebhafter würziger Kräftiger Espresso, keine säure. der Puck ist nach dem Bezug recht nass, liegt wohl auch noch an der frische der Bohnen.",
        "Geschmack": "",
        "Wiederkaufen": "Absolut ! Macht süchtig!!! Top/ Preis leistungsverhältnis!"
    },
    {
        "Full Post": "AW: Ich trinke gerade diesen Espresso.... Name der Bohne: Chikmagalur Karnataka von Torrefazione Giamaica Caffè Packungsgröße: 250 Gramm Gemahlen und Bezogen mit: BB105 / BZ99 und Pavoni Professional Gekauft am: 15.11.2011 MHD: 04/13 (1,5 Jahre Haltbarkeit ab Röstung) Eigenschaften: Hm. Einstellung total easy, Mitte halt. Unkompliziert zu beziehen, bis mal Feintuning will und rumfummelt - als Espresso interessant und kommt aus der Bezzi ganz anders, als aus der Pavoni - mag auch an der Menge liegen. Als Espresso eine Wucht, wirklich voll, schokoladig. Mit Milch kommt das schokoladige ein bisschen durch - insgesamt wird er ein bisschen breiter aufgefächert aber verliert meiner Meinung nach an der Fülle. Kein Wunder, ist ja auch verdünnt. Wieder kaufen: Ja. Nächster: Zum runterkommen wieder Mirella Malabar - mein Standardkaffee. Es steht schon ein Indian Mysore, auch von Torrefazione Giamaica, hier und wird in Kürze probiert. Leider nicht ganz billig im Vergleich... Zu kaufen beim Grenzgänger in München, nähe Ostbahnhof. Grüße!",
        "Name": "Chikmagalur Karnataka von Torrefazione Giamaica Caffè",
        "Packungsgröße": "250 Gramm",
        "Maschine": "BB105 / BZ99 und Pavoni Professional",
        "Gekauft am": "15.11.2011",
        "MHD": "04/13 (1,5 Jahre Haltbarkeit ab Röstung)",
        "Eigenschaften": "Hm. Einstellung total easy, Mitte halt. Unkompliziert zu beziehen, bis mal Feintuning will und rumfummelt - als Espresso interessant und kommt aus der Bezzi ganz anders, als aus der Pavoni - mag auch an der Menge liegen. Als Espresso eine Wucht, wirklich voll, schokoladig. Mit Milch kommt das schokoladige ein bisschen durch - insgesamt wird er ein bisschen breiter aufgefächert aber verliert meiner Meinung nach an der Fülle. Kein Wunder, ist ja auch verdünnt.",
        "Geschmack": "",
        "Wiederkaufen": "Ja. Nächster: Zum runterkommen wieder Mirella Malabar - mein Standardkaffee. Es steht schon ein Indian Mysore, auch von Torrefazione Giamaica, hier und wird in Kürze probiert. Leider nicht ganz billig im Vergleich... Zu kaufen beim Grenzgänger in München, nähe Ostbahnhof. Grüße!"
    },
    {
        "Full Post": "AW: Ich trinke gerade diesen Espresso.... Name der Bohne: Italienische Mischung 60/40 von der Fiaker Kaffeerösterei in Berlin-Moabit Gekauft am: 17.04. Packungsgröße: 500 Gramm (11€) MHD: keins Gemahlen und Bezogen mit: Iberital Challenge, Elektra Cappuccina 9,5 Gramm im Einersieb Eigenschaften: Sehr dunkel geröstet, ölig glänzend. Sie riechen sogar schon ein bisschen rauchig, das ist aber keineswegs unangenehm. Es ist praktisch kein Bruch vorhanden. In der Zubereitung macht er keine großen Probleme, der richtige Mahlgrad etc. war schnell gefunden. In der Tasse riecht er dann gar nicht mehr rauchig, sondern richtig süß. Erst dachte ich an Marzipan, bei einem anderen Shot an Amaretto... achso na klar... es ist Mandelgeruch. Und so toll schmeckt er dann auch. Ich meine eine Note Malz noch herauszuschmecken, wie bei Malzbier. Er ist keine Cremabombe würde ich sagen aber es ist schon genug Crama vorhanden um im Cappuccino eine schöne Latte Art zu zaubern. Dort setzt er sich übrigens auch schön durch. Sehr Lecker. Die beschriebenen Geschmacksnoten kann ich da allerdings nicht mehr herausschmecken. Wieder kaufen: Unbedingt!! [/IMG]",
        "Name": "Italienische Mischung 60/40 von der Fiaker Kaffeerösterei in Berlin-Moabit",
        "Packungsgröße": "500 Gramm (11€)",
        "Maschine": "Iberital Challenge, Elektra Cappuccina 9,5 Gramm im Einersieb",
        "Gekauft am": "17.04.",
        "MHD": "keins",
        "Eigenschaften": "Sehr dunkel geröstet, ölig glänzend. Sie riechen sogar schon ein bisschen rauchig, das ist aber keineswegs unangenehm. Es ist praktisch kein Bruch vorhanden. In der Zubereitung macht er keine großen Probleme, der richtige Mahlgrad etc. war schnell gefunden. In der Tasse riecht er dann gar nicht mehr rauchig, sondern richtig süß. Erst dachte ich an Marzipan, bei einem anderen Shot an Amaretto... achso na klar... es ist Mandelgeruch. Und so toll schmeckt er dann auch. Ich meine eine Note Malz noch herauszuschmecken, wie bei Malzbier. Er ist keine Cremabombe würde ich sagen aber es ist schon genug Crama vorhanden um im Cappuccino eine schöne Latte Art zu zaubern. Dort setzt er sich übrigens auch schön durch. Sehr Lecker. Die beschriebenen snoten kann ich da allerdings nicht mehr herausschmecken.",
        "Geschmack": "",
        "Wiederkaufen": "Unbedingt!! [/IMG]"
    },
    {
        "Full Post": "AW: Ich trinke gerade diesen Espresso.... AW: Ich trinke gerade diesen Espresso.... Name der Bohne: ESPRESSO BUONGUSTAIO Packungsgröße: von 250 Gramm bis x Gemahlen und Bezogen mit: Cuisinart DBM8E/ La pavoni pro. Gekauft am: 26.04.13 röstung 24.04.13 MHD: bis er verbraucht ist 2014 sollte ich nicht mehr trinken Eigenschaften: kräftiger bei etwas mehr Temperatur. Crema gut. Gleicher Eindruck im Cappuccino. Wo auch eine süßliche Säure kommt im Rachen. Abgang lang anhaltend von 80% des kaffees bitter, sauer und nussig hin zu feiner Note. Mit Zucker verschwindet sauer und Früchte kommen durch. Sehr unkomplizierter Kaffee. Wieder kaufen: Ja. Darf in meiner Sammlung nicht fehlen. Bis heute einer der 5 besten. Bei richtigem Umgang!",
        "Name": "ESPRESSO BUONGUSTAIO",
        "Packungsgröße": "von 250 Gramm bis x",
        "Maschine": "Cuisinart DBM8E/ La pavoni pro.",
        "Gekauft am": "26.04.13 röstung 24.04.13",
        "MHD": "bis er verbraucht ist 2014 sollte ich nicht mehr trinken",
        "Eigenschaften": "kräftiger bei etwas mehr Temperatur. Crema gut. Gleicher Eindruck im Cappuccino. Wo auch eine süßliche Säure kommt im Rachen. Abgang lang anhaltend von 80% des kaffees bitter, sauer und nussig hin zu feiner Note. Mit Zucker verschwindet sauer und Früchte kommen durch. Sehr unkomplizierter Kaffee.",
        "Geschmack": "",
        "Wiederkaufen": "Ja. Darf in meiner Sammlung nicht fehlen. Bis heute einer der 5 besten. Bei richtigem Umgang!"
    },
    {
        "Full Post": "AW: Ich trinke gerade diesen Espresso.... Röster: Kaffeemanufaktur Würzburg Name der Bohne: Premium und Buongustaio Packungsgröße: je 250 Gramm Gemahlen und Bezogen mit: Graef CM 90/Nuova Simonelli Personal 1 Gekauft am: je Anfang September 2013 MHD: nicht angegeben Eigenschaften (trifft auf beide Sorten zu): Verpackung einfacher Papierbeutel mit Sortenaufkleber, Bohnen wenig brüchig, leicht ins Ölige geröstet, sehr schwacher Geruch, wenig aromatischer Geruch, braucht sehr lange zum Mahlen und eine relativ feine Mahlgradeinstellung im Vergleich zu SÄMTLICHEN anderen bisher probierten Sorten; In der Tasse der Premium vorne sehr spitz und hinten absolut körperfrei; bis jetzt leider am ehesten zu vergleichchen mit dem aus Neugier probierten Penny-Hausmarken Espresso; der Buongustaio vorne weniger spitz, jedoch ebenso wenig aussagekräftig im weiteren Geschmacksprofil. Ein (fachfremder) Freund, der bei mir sicherlich zwei Mal die Woche zum Kaffee kommt, meinte: \"Also Chris, ich mag ja sehr, was ich normalerweise bei dir bekomme, aber das ist einfach furchtbar. Bist mir jetzt nicht böse, oder?\" (War nicht böse, ahnte es ja selbst...) Wieder kaufen: auf keinen Fall Anmerkungen: Mehrere Kaffeetrinker haben beide Sorten probiert und keiner mochte die Ergebnisse. Geübtere konnten besser beschreiben, was sie nicht mochten, reine Kaffeetrinker meinten einfach, er schmeckt nicht. Ich kann einfach nicht glauben, dass ein Röster (kenne nur die Internetseite) gleich zwei Sorten hat, die so gar nicht gut sind. Ich habe deshalb Proben an Forenmitglieder mit der Bitte verteilt, auf ihrem Equipment zu probieren, damit ich etwas Gewisseheit habe. Ich werde updaten, sobald deren Erfahrungsbericht vorliegt!",
        "Name": "Premium und Buongustaio",
        "Packungsgröße": "je 250 Gramm",
        "Maschine": "Graef CM 90/Nuova Simonelli Personal 1",
        "Gekauft am": "je Anfang September 2013",
        "MHD": "nicht angegeben  (trifft auf beide Sorten zu): Verpackung einfacher Papierbeutel mit Sortenaufkleber, Bohnen wenig brüchig, leicht ins Ölige geröstet, sehr schwacher Geruch, wenig aromatischer Geruch, braucht sehr lange zum Mahlen und eine relativ feine Mahlgradeinstellung im Vergleich zu SÄMTLICHEN anderen bisher probierten Sorten; In der Tasse der Premium vorne sehr spitz und hinten absolut körperfrei; bis jetzt leider am ehesten zu vergleichchen mit dem aus Neugier probierten Penny-Hausmarken Espresso; der Buongustaio vorne weniger spitz, jedoch ebenso wenig aussagekräftig im weiteren sprofil. Ein (fachfremder) Freund, der bei mir sicherlich zwei Mal die Woche zum Kaffee kommt, meinte: \"Also Chris, ich mag ja sehr, was ich normalerweise bei dir bekomme, aber das ist einfach furchtbar. Bist mir jetzt nicht böse, oder?\" (War nicht böse, ahnte es ja selbst...)",
        "Eigenschaften": "",
        "Geschmack": "",
        "Wiederkaufen": "auf keinen Fall Anmerkungen: Mehrere Kaffeetrinker haben beide Sorten probiert und keiner mochte die Ergebnisse. Geübtere konnten besser beschreiben, was sie nicht mochten, reine Kaffeetrinker meinten einfach, er schmeckt nicht. Ich kann einfach nicht glauben, dass ein Röster (kenne nur die Internetseite) gleich zwei Sorten hat, die so gar nicht gut sind. Ich habe deshalb Proben an Forenmitglieder mit der Bitte verteilt, auf ihrem Equipment zu probieren, damit ich etwas Gewisseheit habe. Ich werde updaten, sobald deren Erfahrungsbericht vorliegt!"
    },
    {
        "Full Post": "AW: Ich trinke gerade diesen Espresso.... Zitat von chrisjoerg: ↑ Röster: Kaffeemanufaktur Würzburg Name der Bohne: Premium und Buongustaio Packungsgröße: je 250 Gramm Gemahlen und Bezogen mit: Graef CM 90/Nuova Simonelli Personal 1 Gekauft am: je Anfang September 2013 MHD: nicht angegeben Eigenschaften (trifft auf beide Sorten zu): Verpackung einfacher Papierbeutel mit Sortenaufkleber, Bohnen wenig brüchig, leicht ins Ölige geröstet, sehr schwacher Geruch, wenig aromatischer Geruch, braucht sehr lange zum Mahlen und eine relativ feine Mahlgradeinstellung im Vergleich zu SÄMTLICHEN anderen bisher probierten Sorten; In der Tasse der Premium vorne sehr spitz und hinten absolut körperfrei; bis jetzt leider am ehesten zu vergleichchen mit dem aus Neugier probierten Penny-Hausmarken Espresso; der Buongustaio vorne weniger spitz, jedoch ebenso wenig aussagekräftig im weiteren Geschmacksprofil. Ein (fachfremder) Freund, der bei mir sicherlich zwei Mal die Woche zum Kaffee kommt, meinte: \"Also Chris, ich mag ja sehr, was ich normalerweise bei dir bekomme, aber das ist einfach furchtbar. Bist mir jetzt nicht böse, oder?\" (War nicht böse, ahnte es ja selbst...) Wieder kaufen: auf keinen Fall Anmerkungen: Mehrere Kaffeetrinker haben beide Sorten probiert und keiner mochte die Ergebnisse. Geübtere konnten besser beschreiben, was sie nicht mochten, reine Kaffeetrinker meinten einfach, er schmeckt nicht. Ich kann einfach nicht glauben, dass ein Röster (kenne nur die Internetseite) gleich zwei Sorten hat, die so gar nicht gut sind. Ich habe deshalb Proben an Forenmitglieder mit der Bitte verteilt, auf ihrem Equipment zu probieren, damit ich etwas Gewisseheit habe. Ich werde updaten, sobald deren Erfahrungsbericht vorliegt! Klicke in dieses Feld, um es in vollständiger Größe anzuzeigen. Habe neue Erkenntnisse nach Verteilaktion an Forenmitglieder gewonnen. Forenmitglied 1: \"Der schmeckte so, wie er gerochen hat.\" (Dualboiler PID) Forenmitglied 2: \"Konnte ihn nicht aufbrauchen.\" (Mechanika / Casa) Ich schließe daher Bedienerfehler aus. Werde aber die manufaktur aufsuchen, wenn ich in würzburg bin und dort vor ort testen. Gruß! Chris",
        "Name": "Premium und Buongustaio",
        "Packungsgröße": "je 250 Gramm",
        "Maschine": "Graef CM 90/Nuova Simonelli Personal 1",
        "Gekauft am": "je Anfang September 2013",
        "MHD": "nicht angegeben  (trifft auf beide Sorten zu): Verpackung einfacher Papierbeutel mit Sortenaufkleber, Bohnen wenig brüchig, leicht ins Ölige geröstet, sehr schwacher Geruch, wenig aromatischer Geruch, braucht sehr lange zum Mahlen und eine relativ feine Mahlgradeinstellung im Vergleich zu SÄMTLICHEN anderen bisher probierten Sorten; In der Tasse der Premium vorne sehr spitz und hinten absolut körperfrei; bis jetzt leider am ehesten zu vergleichchen mit dem aus Neugier probierten Penny-Hausmarken Espresso; der Buongustaio vorne weniger spitz, jedoch ebenso wenig aussagekräftig im weiteren sprofil. Ein (fachfremder) Freund, der bei mir sicherlich zwei Mal die Woche zum Kaffee kommt, meinte: \"Also Chris, ich mag ja sehr, was ich normalerweise bei dir bekomme, aber das ist einfach furchtbar. Bist mir jetzt nicht böse, oder?\" (War nicht böse, ahnte es ja selbst...)",
        "Eigenschaften": "",
        "Geschmack": "",
        "Wiederkaufen": "auf keinen Fall Anmerkungen: Mehrere Kaffeetrinker haben beide Sorten probiert und keiner mochte die Ergebnisse. Geübtere konnten besser beschreiben, was sie nicht mochten, reine Kaffeetrinker meinten einfach, er schmeckt nicht. Ich kann einfach nicht glauben, dass ein Röster (kenne nur die Internetseite) gleich zwei Sorten hat, die so gar nicht gut sind. Ich habe deshalb Proben an Forenmitglieder mit der Bitte verteilt, auf ihrem Equipment zu probieren, damit ich etwas Gewisseheit habe. Ich werde updaten, sobald deren Erfahrungsbericht vorliegt! Klicke in dieses Feld, um es in vollständiger Größe anzuzeigen. Habe neue Erkenntnisse nach Verteilaktion an Forenmitglieder gewonnen. Forenmitglied 1: \"Der schmeckte so, wie er gerochen hat.\" (Dualboiler PID) Forenmitglied 2: \"Konnte ihn nicht aufbrauchen.\" (Mechanika / Casa) Ich schließe daher Bedienerfehler aus. Werde aber die manufaktur aufsuchen, wenn ich in würzburg bin und dort vor ort testen. Gruß! Chris"
    },
    {
        "Full Post": "Röster: Kaffeemanufaktur Würzburg Name der Bohne: Premium und Buongustaio Packungsgröße: je 250 Gramm Gemahlen und Bezogen mit: Graef CM 90/Nuova Simonelli Personal 1 Gekauft am: je Anfang September 2013 MHD: nicht angegeben Eigenschaften (trifft auf beide Sorten zu): Verpackung einfacher Papierbeutel mit Sortenaufkleber, Bohnen wenig brüchig, leicht ins Ölige geröstet, sehr schwacher Geruch, wenig aromatischer Geruch, braucht sehr lange zum Mahlen und eine relativ feine Mahlgradeinstellung im Vergleich zu SÄMTLICHEN anderen bisher probierten Sorten; In der Tasse der Premium vorne sehr spitz und hinten absolut körperfrei; bis jetzt leider am ehesten zu vergleichchen mit dem aus Neugier probierten Penny-Hausmarken Espresso; der Buongustaio vorne weniger spitz, jedoch ebenso wenig aussagekräftig im weiteren Geschmacksprofil. Ein (fachfremder) Freund, der bei mir sicherlich zwei Mal die Woche zum Kaffee kommt, meinte: \"Also Chris, ich mag ja sehr, was ich normalerweise bei dir bekomme, aber das ist einfach furchtbar. Bist mir jetzt nicht böse, oder?\" (War nicht böse, ahnte es ja selbst...) Wieder kaufen: auf keinen Fall Anmerkungen: Mehrere Kaffeetrinker haben beide Sorten probiert und keiner mochte die Ergebnisse. Geübtere konnten besser beschreiben, was sie nicht mochten, reine Kaffeetrinker meinten einfach, er schmeckt nicht. Ich kann einfach nicht glauben, dass ein Röster (kenne nur die Internetseite) gleich zwei Sorten hat, die so gar nicht gut sind. Ich habe deshalb Proben an Forenmitglieder mit der Bitte verteilt, auf ihrem Equipment zu probieren, damit ich etwas Gewisseheit habe. Ich werde updaten, sobald deren Erfahrungsbericht vorliegt! Klicke in dieses Feld, um es in vollständiger Größe anzuzeigen.",
        "Name": "Premium und Buongustaio",
        "Packungsgröße": "je 250 Gramm",
        "Maschine": "Graef CM 90/Nuova Simonelli Personal 1",
        "Gekauft am": "je Anfang September 2013",
        "MHD": "nicht angegeben  (trifft auf beide Sorten zu): Verpackung einfacher Papierbeutel mit Sortenaufkleber, Bohnen wenig brüchig, leicht ins Ölige geröstet, sehr schwacher Geruch, wenig aromatischer Geruch, braucht sehr lange zum Mahlen und eine relativ feine Mahlgradeinstellung im Vergleich zu SÄMTLICHEN anderen bisher probierten Sorten; In der Tasse der Premium vorne sehr spitz und hinten absolut körperfrei; bis jetzt leider am ehesten zu vergleichchen mit dem aus Neugier probierten Penny-Hausmarken Espresso; der Buongustaio vorne weniger spitz, jedoch ebenso wenig aussagekräftig im weiteren sprofil. Ein (fachfremder) Freund, der bei mir sicherlich zwei Mal die Woche zum Kaffee kommt, meinte: \"Also Chris, ich mag ja sehr, was ich normalerweise bei dir bekomme, aber das ist einfach furchtbar. Bist mir jetzt nicht böse, oder?\" (War nicht böse, ahnte es ja selbst...)",
        "Eigenschaften": "",
        "Geschmack": "",
        "Wiederkaufen": "auf keinen Fall Anmerkungen: Mehrere Kaffeetrinker haben beide Sorten probiert und keiner mochte die Ergebnisse. Geübtere konnten besser beschreiben, was sie nicht mochten, reine Kaffeetrinker meinten einfach, er schmeckt nicht. Ich kann einfach nicht glauben, dass ein Röster (kenne nur die Internetseite) gleich zwei Sorten hat, die so gar nicht gut sind. Ich habe deshalb Proben an Forenmitglieder mit der Bitte verteilt, auf ihrem Equipment zu probieren, damit ich etwas Gewisseheit habe. Ich werde updaten, sobald deren Erfahrungsbericht vorliegt! Klicke in dieses Feld, um es in vollständiger Größe anzuzeigen."
    },
    {
        "Full Post": "AW: Ich trinke gerade diesen Espresso.... Name der Bohne: Caffé Pol Packungsgröße: 1.000 Gramm Gemahlen und Bezogen mit: Gastroback Advanced / Gaggia Classic, 2er Sieb, bodenloser Siebträger Gekauft am: vor 3 Wochen MHD: frisch Eigenschaften: 40% Robusta, Cremamonster!, süditalienische Röstung, hat Dampf Sehr unkomplizierter Kaffee. Wieder kaufen: Ja.",
        "Name": "Caffé Pol",
        "Packungsgröße": "1.000 Gramm",
        "Maschine": "Gastroback Advanced / Gaggia Classic, 2er Sieb, bodenloser Siebträger",
        "Gekauft am": "vor 3 Wochen",
        "MHD": "frisch",
        "Eigenschaften": "40% Robusta, Cremamonster!, süditalienische Röstung, hat Dampf Sehr unkomplizierter Kaffee.",
        "Geschmack": "",
        "Wiederkaufen": "Ja."
    },
    {
        "Full Post": "AW: Ich trinke gerade diesen Espresso.... Name der Bohne: Ulmer Tor Mischung Rösterei: Kaffeerösterei Simon - Startseite Packungsgröße: 500 Gramm Gemahlen und Bezogen mit: Gastroback Advanced Mühle / Gaggia Classic, 2er Sieb, bodenloser Siebträger Gekauft am: 3. Januar 2014 MHD: gemahlen vor 3 Wochen Eigenschaften: 100% Arabica, milde Mischung, trotz sehr dunkler Röstung, richtig dicke, glänzende Bohnen! Sehen super aus Die Crema war überraschend üppig und mit Tigermuster Geschmack angenehm, kann ihn nach der 1. Tasse noch nicht ganz einordnen. Die Bohnen sind extrem ergiebig. Wieder kaufen: Ja!!!!! Unbedingt!",
        "Name": "Ulmer Tor Mischung Rösterei: Kaffeerösterei Simon - Startseite",
        "Packungsgröße": "500 Gramm",
        "Maschine": "Gastroback Advanced Mühle / Gaggia Classic, 2er Sieb, bodenloser Siebträger",
        "Gekauft am": "3. Januar 2014",
        "MHD": "gemahlen vor 3 Wochen",
        "Eigenschaften": "100% Arabica, milde Mischung, trotz sehr dunkler Röstung, richtig dicke, glänzende Bohnen! Sehen super aus Die Crema war überraschend üppig und mit Tigermuster  angenehm, kann ihn nach der 1. Tasse noch nicht ganz einordnen. Die Bohnen sind extrem ergiebig.",
        "Geschmack": "",
        "Wiederkaufen": "Ja!!!!! Unbedingt!"
    },
    {
        "Full Post": "AW: Ich trinke gerade diesen Espresso.... Name der Bohne: Quijote Quamäleon Packungsgröße: 250 Gramm Gemahlen und Bezogen mit: Bezzerra Strega/005 Gekauft am: Anfang Februar Röstdatum: 20.01.2014, Trinkreife nach 14 Tagen Eigenschaften: Schnell einzustellen, tolle Crema, keineswegs bitter oder sauer, eher ein Gaumenschmeichler, schön zartbitter-schokoladig. Sehr unkomplizierter Kaffee. Wieder kaufen: Ja.",
        "Name": "Quijote Quamäleon",
        "Packungsgröße": "250 Gramm",
        "Maschine": "Bezzerra Strega/005",
        "Gekauft am": "Anfang Februar Röstdatum: 20.01.2014, Trinkreife nach 14 Tagen",
        "MHD": "",
        "Eigenschaften": "Schnell einzustellen, tolle Crema, keineswegs bitter oder sauer, eher ein Gaumenschmeichler, schön zartbitter-schokoladig. Sehr unkomplizierter Kaffee.",
        "Geschmack": "",
        "Wiederkaufen": "Ja."
    },
    {
        "Full Post": "AW: Ich trinke gerade diesen Espresso.... Name der Bohne: IZZO Supermiscela Packungsgröße: 1000 Gramm Gemahlen und Bezogen mit: SAB Alice Gekauft am: Anfang Februar Eigenschaften: braucht hohe Temperatur, bin hier noch nicht am Optimum - Samtig, dickflüssig, schokoladik unkomplizierter Kaffee. Wieder kaufen: unbedingt",
        "Name": "IZZO Supermiscela",
        "Packungsgröße": "1000 Gramm",
        "Maschine": "SAB Alice",
        "Gekauft am": "Anfang Februar",
        "MHD": "",
        "Eigenschaften": "braucht hohe Temperatur, bin hier noch nicht am Optimum - Samtig, dickflüssig, schokoladik unkomplizierter Kaffee.",
        "Geschmack": "",
        "Wiederkaufen": "unbedingt"
    },
    {
        "Full Post": "AW: Ich trinke gerade diesen Espresso.... Röster: Baumkaffee Name der Bohne: Special Roast 14.2 Packungsgröße: 500 Gramm Röstdatum: 6.2.2014 Gekauft am: 6.2.2014 Gemahlen mit: Mahlkönig Vario Home v2 Bezogen mit: La Spaziale Vivaldi II Eigenschaften: läuft wie Schokolade, schmeckt mir als altem Augschburgo-Trinker sogar noch einen Tick besser, süßer, nussiger. Ist sehr einfach einzustellen, unkompliziert. Auch im Frühstücks-Cappuccino das leckerste, was ich seit langem probiert habe Wieder kaufen: Definitiv!",
        "Name": "Special Roast 14.2",
        "Packungsgröße": "500 Gramm Röstdatum: 6.2.2014",
        "Maschine": "",
        "Gekauft am": "6.2.2014 Gemahlen mit: Mahlkönig Vario Home v2 Bezogen mit: La Spaziale Vivaldi II",
        "MHD": "",
        "Eigenschaften": "läuft wie Schokolade, schmeckt mir als altem Augschburgo-Trinker sogar noch einen Tick besser, süßer, nussiger. Ist sehr einfach einzustellen, unkompliziert. Auch im Frühstücks-Cappuccino das leckerste, was ich seit langem probiert habe",
        "Geschmack": "",
        "Wiederkaufen": "Definitiv!"
    },
    {
        "Full Post": "Name der Bohne: Hagen Kaffee Cinque Belle Packungsgröße: 250 Gramm Gemahlen und Bezogen mit: Mazzer Mini E/SJ, Dalla Corte Mini Gekauft am: Anfang Mai MHD: 03/15 Eigenschaften: Mahlgrad sehr schnell gefunden. Kaffee Schmeckt nach pyromanisches Feuerritual. Erste Geschmacksnotiz: Chemisch verbrannt. Laut Webseite \"etwas dunkler geröstet\". Das Zeug schmeckt schon in der Stufe \"etwas\" nach Aschenbecher. Ich kann einfach nichts nettes an dem Kaffee Finden. Hatte mal Bohnen vom Aldi zum einmahlen, erinnert mich sehr daran. Bohnen sehen sehr ölig aus. Wieder kaufen: Auf keinen Fall.",
        "Name": "Hagen Kaffee Cinque Belle",
        "Packungsgröße": "250 Gramm",
        "Maschine": "Mazzer Mini E/SJ, Dalla Corte Mini",
        "Gekauft am": "Anfang Mai",
        "MHD": "03/15",
        "Eigenschaften": "Mahlgrad sehr schnell gefunden. Kaffee Schmeckt nach pyromanisches Feuerritual. Erste snotiz: Chemisch verbrannt. Laut Webseite \"etwas dunkler geröstet\". Das Zeug schmeckt schon in der Stufe \"etwas\" nach Aschenbecher. Ich kann einfach nichts nettes an dem Kaffee Finden. Hatte mal Bohnen vom Aldi zum einmahlen, erinnert mich sehr daran. Bohnen sehen sehr ölig aus.",
        "Geschmack": "",
        "Wiederkaufen": "Auf keinen Fall."
    },
    {
        "Full Post": "Zitat von beelte: ↑ Name der Bohne: Hagen Kaffee Cinque Belle Packungsgröße: 250 Gramm Gemahlen und Bezogen mit: Mazzer Mini E/SJ, Dalla Corte Mini Gekauft am: Anfang Mai MHD: 03/15 Eigenschaften: Mahlgrad sehr schnell gefunden. Kaffee Schmeckt nach pyromanisches Feuerritual. Erste Geschmacksnotiz: Chemisch verbrannt. Laut Webseite \"etwas dunkler geröstet\". Das Zeug schmeckt schon in der Stufe \"etwas\" nach Aschenbecher. Ich kann einfach nichts nettes an dem Kaffee Finden. Hatte mal Bohnen vom Aldi zum einmahlen, erinnert mich sehr daran. Bohnen sehen sehr ölig aus. Wieder kaufen: Auf keinen Fall.Klicke in dieses Feld, um es in vollständiger Größe anzuzeigen. Bei dem MHD würde ich mich auch nicht wundern Chemisch verbrannt? Bestimmt eher umgesetzt, was der Chemiehonk als Reaktion zu CO2, H2O, alles geschmacksneutrale Stoffe beschreiben würde. Wenn es dann nach nichts schmeckt, hast du immerhin gut umgesetzt!",
        "Name": "Hagen Kaffee Cinque Belle",
        "Packungsgröße": "250 Gramm",
        "Maschine": "Mazzer Mini E/SJ, Dalla Corte Mini",
        "Gekauft am": "Anfang Mai",
        "MHD": "03/15",
        "Eigenschaften": "Mahlgrad sehr schnell gefunden. Kaffee Schmeckt nach pyromanisches Feuerritual. Erste snotiz: Chemisch verbrannt. Laut Webseite \"etwas dunkler geröstet\". Das Zeug schmeckt schon in der Stufe \"etwas\" nach Aschenbecher. Ich kann einfach nichts nettes an dem Kaffee Finden. Hatte mal Bohnen vom Aldi zum einmahlen, erinnert mich sehr daran. Bohnen sehen sehr ölig aus.",
        "Geschmack": "",
        "Wiederkaufen": "Auf keinen Fall.Klicke in dieses Feld, um es in vollständiger Größe anzuzeigen. Bei dem  würde ich mich auch nicht wundern Chemisch verbrannt? Bestimmt eher umgesetzt, was der Chemiehonk als Reaktion zu CO2, H2O, alles geschmacksneutrale Stoffe beschreiben würde. Wenn es dann nach nichts schmeckt, hast du immerhin gut umgesetzt!"
    },
    {
        "Full Post": "Name der Bohne: Hagen Kaffee Cinque Belle Packungsgröße: 250 Gramm Gemahlen und Bezogen mit: Mazzer Mini E/SJ, Dalla Corte Mini Gekauft am: Anfang Mai MHD: 03/15 Eigenschaften: Mahlgrad sehr schnell gefunden. Kaffee Schmeckt nach pyromanisches Feuerritual. Erste Geschmacksnotiz: Chemisch verbrannt. Laut Webseite \"etwas dunkler geröstet\". Das Zeug schmeckt schon in der Stufe \"etwas\" nach Aschenbecher. Ich kann einfach nichts nettes an dem Kaffee Finden. Hatte mal Bohnen vom Aldi zum einmahlen, erinnert mich sehr daran. Bohnen sehen sehr ölig aus. Wieder kaufen: Auf keinen Fall.Klicke in dieses Feld, um es in vollständiger Größe anzuzeigen.",
        "Name": "Hagen Kaffee Cinque Belle",
        "Packungsgröße": "250 Gramm",
        "Maschine": "Mazzer Mini E/SJ, Dalla Corte Mini",
        "Gekauft am": "Anfang Mai",
        "MHD": "03/15",
        "Eigenschaften": "Mahlgrad sehr schnell gefunden. Kaffee Schmeckt nach pyromanisches Feuerritual. Erste snotiz: Chemisch verbrannt. Laut Webseite \"etwas dunkler geröstet\". Das Zeug schmeckt schon in der Stufe \"etwas\" nach Aschenbecher. Ich kann einfach nichts nettes an dem Kaffee Finden. Hatte mal Bohnen vom Aldi zum einmahlen, erinnert mich sehr daran. Bohnen sehen sehr ölig aus.",
        "Geschmack": "",
        "Wiederkaufen": "Auf keinen Fall.Klicke in dieses Feld, um es in vollständiger Größe anzuzeigen."
    },
    {
        "Full Post": "Name der Bohne: Machhörndl Esmeralda Morales Packungsgröße: 250 Gramm Gemahlen und Bezogen mit: Mazzer Mini E/SJ, Dalla Corte Mini Gekauft am: Anfang Juni MHD: Super frisch Eigenschaften: Mahlgrad ist deutlich feiner als die Bohnen die ich vorher hatte. Ca. 10sec für 16g. Brühtemperatur bei 93°C. 40g in der Tasse finde ich als optimal. Bei einem Extraktionsverhältnis von 1:2 ist er mir zu intensiv. Klassisch 50g in der Tasse geht auch. Bei 40g passt es aber auch sehr gut als Cappuchino bei dem dann sehr toll die schokoladigen Noten hervorkommen. Ein toller Kaffee auch für in den Cappuchino. Als Espresso setzen sich dann aber zu der Schokolade auch fruchtige Aromen durch. Die Beschreibung \"dunkle Beeren\" beschreibt es ganz gut. Ich meine aber auch noch süßen Pfirsisch zu schmecken. Der Espresso ist syrupartig und sehr fein cremig. Echt sehr sehr lecker das Zeug. Wieder kaufen: Bestimmt.",
        "Name": "Machhörndl Esmeralda Morales",
        "Packungsgröße": "250 Gramm",
        "Maschine": "Mazzer Mini E/SJ, Dalla Corte Mini",
        "Gekauft am": "Anfang Juni",
        "MHD": "Super frisch",
        "Eigenschaften": "Mahlgrad ist deutlich feiner als die Bohnen die ich vorher hatte. Ca. 10sec für 16g. Brühtemperatur bei 93°C. 40g in der Tasse finde ich als optimal. Bei einem Extraktionsverhältnis von 1:2 ist er mir zu intensiv. Klassisch 50g in der Tasse geht auch. Bei 40g passt es aber auch sehr gut als Cappuchino bei dem dann sehr toll die schokoladigen Noten hervorkommen. Ein toller Kaffee auch für in den Cappuchino. Als Espresso setzen sich dann aber zu der Schokolade auch fruchtige Aromen durch. Die Beschreibung \"dunkle Beeren\" beschreibt es ganz gut. Ich meine aber auch noch süßen Pfirsisch zu schmecken. Der Espresso ist syrupartig und sehr fein cremig. Echt sehr sehr lecker das Zeug.",
        "Geschmack": "",
        "Wiederkaufen": "Bestimmt."
    },
    {
        "Full Post": "Name der Bohne: Machhörndl Kenia Kibiruini Packungsgröße: 250 Gramm Gemahlen und Bezogen mit: Mazzer Mini E/SJ, Dalla Corte Mini Gekauft am: Anfang Juni MHD: 02.12.15 Eigenschaften: 95°C, 18g Mehl bei 42g in der Tasse habe ich für optimal herausgefunden. Hatte den Kaffee vorher im kleineren Sieb mit 16g zubereitet, dann trat aber eher die Säure in den Vordergrund. Wenn man zu sehr in Richtung Ristretto geht, wird der Kaffee rechn schnell sehr dicht vom Geschmack her und mich schüttelt es. Ich finde das die Beschreibung von Machhörndl immer sehr gut passt. Saftiger Espresso. Nicht mein Ding, aber ich versuche mich immer mal wieder an dem hellen Zeug. Lande dann wieder bei dem dunkleren Röstungen. Sicher ein interessanter Espresso, ich mag es nicht jeden Tag. Wieder kaufen: Nein.",
        "Name": "Machhörndl Kenia Kibiruini",
        "Packungsgröße": "250 Gramm",
        "Maschine": "Mazzer Mini E/SJ, Dalla Corte Mini",
        "Gekauft am": "Anfang Juni",
        "MHD": "02.12.15",
        "Eigenschaften": "95°C, 18g Mehl bei 42g in der Tasse habe ich für optimal herausgefunden. Hatte den Kaffee vorher im kleineren Sieb mit 16g zubereitet, dann trat aber eher die Säure in den Vordergrund. Wenn man zu sehr in Richtung Ristretto geht, wird der Kaffee rechn schnell sehr dicht vom  her und mich schüttelt es. Ich finde das die Beschreibung von Machhörndl immer sehr gut passt. Saftiger Espresso. Nicht mein Ding, aber ich versuche mich immer mal wieder an dem hellen Zeug. Lande dann wieder bei dem dunkleren Röstungen. Sicher ein interessanter Espresso, ich mag es nicht jeden Tag.",
        "Geschmack": "",
        "Wiederkaufen": "Nein."
    },
    {
        "Full Post": "Guten Abend! Ich möchte mich auch mal an diesem Thema beteiligen, da ich heute quasi in höhere Sphären aufgestiegen bin, was den Kaffeegenuss angeht. Zum ersten Mal frisch geröstete Bohen aus der kleinen Rösterei hier in Braunschweig. Und was soll ich sagen? Wie konnte ich das, was ich vorher getan habe, eigentlich Kaffeetrinken nennen?! Name der Bohne: Espresso Intenso Uno Herkunft: Guatemala, Region Antigua Packungsgröße: 250 Gramm Gekauft bei: Kaffee-Fabrik Braunschweig, https://kaffee-fabrik.de Geröstet am: 04.01.2016 Gekauft am: 12.01.2016 MHD: 08.01.2017 Gemahlen und Bezogen mit: Graef CM800 / Saeco Aroma Nero Eigenschaften: Die Bohnen sehen sehr gut aus, laut Verkäufer/Chef(?) handverlesen, gleichmäßig geröstet, eher hell. Die Menge für einen Doppio hab ich nach Gefühl abgeschätzt, aber auf Anhieb ein recht gutes Ergebnis gehabt, ca. 25 sec Durchlaufzeit. Ich habe kaum vernünftige Vergleichsmöglichkeiten, aber der Espresso ist wirklich gut! Sehr fruchtig, beinahe süßlich, im Abgang ein wenig schokoladig und es klingt Säure mit an, aber nur dezent. Wieder kaufen: Ohja! Vor allem, weil der Mensch hinter dem Tresen wirklich Ahnung hatte von seinem Kaffee. Mit freundlichen Grüßen Leviathan PS: @Pertlwieser Puh, gleichzeitig gepostet",
        "Name": "Espresso Intenso Uno Herkunft: Guatemala, Region Antigua",
        "Packungsgröße": "250 Gramm Gekauft bei: Kaffee-Fabrik Braunschweig, https://kaffee-fabrik.de Geröstet am: 04.01.2016",
        "Maschine": "Graef CM800 / Saeco Aroma Nero",
        "Gekauft am": "12.01.2016",
        "MHD": "08.01.2017",
        "Eigenschaften": "Die Bohnen sehen sehr gut aus, laut Verkäufer/Chef(?) handverlesen, gleichmäßig geröstet, eher hell. Die Menge für einen Doppio hab ich nach Gefühl abgeschätzt, aber auf Anhieb ein recht gutes Ergebnis gehabt, ca. 25 sec Durchlaufzeit. Ich habe kaum vernünftige Vergleichsmöglichkeiten, aber der Espresso ist wirklich gut! Sehr fruchtig, beinahe süßlich, im Abgang ein wenig schokoladig und es klingt Säure mit an, aber nur dezent.",
        "Geschmack": "",
        "Wiederkaufen": "Ohja! Vor allem, weil der Mensch hinter dem Tresen wirklich Ahnung hatte von seinem Kaffee. Mit freundlichen Grüßen Leviathan PS: @Pertlwieser Puh, gleichzeitig gepostet"
    },
    {
        "Full Post": "Name der Bohne: 3M Espresso von Machwitz Kaffee Packungsgröße: 1000 Gramm Gemahlen und Bezogen mit: Macap manuale / Gastroback Espressomaschine Design Espresso Advanced Control 42636 Gekauft am: April 2016 MHD: 03/17 Eigenschaften: Gibt bei der Bohne eigentlich keine Überextraktion, sehr harmonisch im Cappuchino, konstante Qualität - kaufe ich seit Jahren in deren guten Onlineshop Wieder kaufen: Ja.",
        "Name": "3M Espresso von Machwitz Kaffee",
        "Packungsgröße": "1000 Gramm",
        "Maschine": "Macap manuale / Gastroback Espressomaschine Design Espresso Advanced Control 42636",
        "Gekauft am": "April 2016",
        "MHD": "03/17",
        "Eigenschaften": "Gibt bei der Bohne eigentlich keine Überextraktion, sehr harmonisch im Cappuchino, konstante Qualität - kaufe ich seit Jahren in deren guten Onlineshop",
        "Geschmack": "",
        "Wiederkaufen": "Ja."
    },
    {
        "Full Post": "Name der Bohne: Casanova Packungsgröße: 250 Gramm Gemahlen und Bezogen mit: \"Der Kaffeeladen\" in Mannheim, Lindenhof Gekauft am: 11.02.2017 MHD: k.A. Eigenschaften: Kräftiger Espresso mit einem \"feinen Hauch von Zartbitter\". Venezianische Röstung. Brasilien, Indien, Äthiopien. 100% Arabica Sowohl meine Zunge als auch meine retronasale Wahrnehmung sind leider nicht derart sensibel, dass ich derart differenziert mein Geschmackserlebnis schildern könnte. Ich kann nur sagen: Er schmeckt mir sehr, sehr gut. Wieder kaufen: Ja.",
        "Name": "Casanova",
        "Packungsgröße": "250 Gramm",
        "Maschine": "\"Der Kaffeeladen\" in Mannheim, Lindenhof",
        "Gekauft am": "11.02.2017",
        "MHD": "k.A.",
        "Eigenschaften": "Kräftiger Espresso mit einem \"feinen Hauch von Zartbitter\". Venezianische Röstung. Brasilien, Indien, Äthiopien. 100% Arabica Sowohl meine Zunge als auch meine retronasale Wahrnehmung sind leider nicht derart sensibel, dass ich derart differenziert mein serlebnis schildern könnte. Ich kann nur sagen: Er schmeckt mir sehr, sehr gut.",
        "Geschmack": "",
        "Wiederkaufen": "Ja."
    }
]